Workbook
Name _1试算平衡表期间_2006年第6期__: #REF!
Name _2试算平衡表期间_2006年第7期__: #REF!
Name 表页_1: 利润表!#REF!
Name 表页_1: 资产负债表!$A$5:$H$79
Name 会计分录序时簿: #REF!

Sheet 银行流水账
A1: 银行账户明细账
A2: 日期 | B2: 账户初始资金 | C2: 交易序号 | D2: 存款增加 | E2: 存款减少 | F2: 账户余额 | G2: 交易简述 | H2: 对方科目 | I2: 现金流性质分析 | M2: 流动资产 | N2: 现金
D3: 0 | F3: =B3+D3-E3 -> 0 | N3: 银行存款 | P3: 经营活动产生的现金流量 | Q3: 取得的销售货物收到的现金
A4: 46232 | F4: =F3+D4-E4 -> 0 | N4: 短期投资 | Q4: 取得的提供服务到的现金
A5: 46232 | F5: =F4+D5-E5 -> 0 | N5: 应收票据 | Q5: 收取利息、手续费及佣金的现金
A6: 46232 | F6: =F5+D6-E6 -> 0 | N6: 应收股利 | Q6: 处置交易性金融资产净增加额
A7: 46232 | F7: =F6+D7-E7 -> 0 | N7: 应收利息 | Q7: 回购业务资金净增加额
A8: 46232 | F8: =F7+D8-E8 -> 0 | N8: 应收账款 | Q8: 收到其他与经营活动有关的现金
A9: 46232 | F9: =F8+D9-E9 -> 0 | N9: 坏账准备 | Q9: 支付给职工以及为职工支付的现金
A10: 46232 | F10: =F9+D10-E10 -> 0 | N10: 其他应收款 | Q10: 支付的各项税费
A11: 46232 | F11: =F10+D11-E11 -> 0 | N11: 预付账款 | Q11: 回购业务资金净减少额
A12: 46232 | F12: =F11+D12-E12 -> 0 | N12: 应收补贴款 | Q12: 支付其他与经营活动有关的现金
A13: 46232 | F13: =F12+D13-E13 -> 0 | N13: 存货 | P13: 投资活动产生的现金流量 | Q13: 收回投资收到的现金
A14: 46232 | F14: =F13+D14-E14 -> 0 | N14: 存货变现琐事准备 | Q14: 取得投资收益收到的现金
A15: 46232 | F15: =F14+D15-E15 -> 0 | N15: 待摊费用 | Q15: 处置固定资产、无形资产和其他长期资产收到的现金净额
A16: 46232 | F16: =F15+D16-E16 -> 0 | N16: 1年内到期的长期债券投资 | Q16: 收到其他与投资活动有关的现金
A17: 46232 | F17: =F16+D17-E17 -> 0 | N17: 其他流动资产 | Q17: 投资支付现金
A18: 46232 | F18: =F17+D18-E18 -> 0 | M18: 长期投资 | N18: 长期股权投资 | Q18: 购建固定资产、无形资产和其他长期资产支付的现金
A19: 46232 | F19: =F18+D19-E19 -> 0 | N19: 长期债权投资 | Q19: 吸收投资收到的现金
A20: 46232 | F20: =F19+D20-E20 -> 0 | M20: 固定资产 | N20: 固定资产原价 | P20: 筹资活动产生的现金流量 | Q20: 取得借款收到的现金
A21: 46232 | F21: =F20+D21-E21 -> 0 | N21: 固定资产累计折旧 | Q21: 收到其他与筹资活动有关的现金
A22: 46232 | F22: =F21+D22-E22 -> 0 | N22: 固定资产减值准备 | Q22: 偿还债务支付的现金
A23: 46232 | F23: =F22+D23-E23 -> 0 | N23: 工程物资 | Q23: 分配股利、利润或偿付利息支付的现金
A24: 46232 | F24: =F23+D24-E24 -> 0 | N24: 在建工程 | Q24: 支付其他与筹资活动有关的现金
A25: 46232 | F25: =F24+D25-E25 -> 0 | N25: 固定资产清理
A26: 46232 | F26: =F25+D26-E26 -> 0 | N26: 土地使用权
A27: 46232 | F27: =F26+D27-E27 -> 0 | N27: 工业产权及专有技术
A28: 46232 | F28: =F27+D28-E28 -> 0 | N28: 其他无形资产
A29: 46232 | F29: =F28+D29-E29 -> 0 | N29: 开办费
A30: 46232 | F30: =F29+D30-E30 -> 0 | N30: 其他长期资产
A31: 46054 | F31: =F30+D31-E31 -> 0 | M31: 负债 | N31: 短期借款
A32: 46054 | F32: =F31+D32-E32 -> 0 | N32: 应付票据
A33: 46054 | F33: =F32+D33-E33 -> 0 | N33: 应付账款
A34: 46054 | F34: =F33+D34-E34 -> 0 | N34: 预收账款
A35: 46054 | F35: =F34+D35-E35 -> 0 | N35: 应付工资
A36: 46054 | F36: =F35+D36-E36 -> 0 | N36: 应付福利费
A37: 46054 | F37: =F36+D37-E37 -> 0 | N37: 应付股利
A38: 46054 | F38: =F37+D38-E38 -> 0 | N38: 应交税金
A39: 46054 | F39: =F38+D39-E39 -> 0 | N39: 其他应交款
A40: 46054 | F40: =F39+D40-E40 -> 0 | N40: 其他应付款
A41: 46054 | F41: =F40+D41-E41 -> 0 | N41: 预提费用
A42: 46054 | F42: =F41+D42-E42 -> 0 | N42: 预计负债
A43: 46054 | F43: =F42+D43-E43 -> 0 | N43: 1年内到期的长期负债
A44: 46054 | F44: =F43+D44-E44 -> 0 | N44: 其他流动负债
A45: 46054 | F45: =F44+D45-E45 -> 0 | M45: 长期负债 | N45: 长期借款
A46: 46054 | F46: =F45+D46-E46 -> 0 | N46: 应付债券
A47: 46054 | F47: =F46+D47-E47 -> 0 | N47: 长期应付款
A48: 46054 | F48: =F47+D48-E48 -> 0 | N48: 专项应付款
A49: 46054 | F49: =F48+D49-E49 -> 0 | N49: 其他长期负债
A50: 46054 | F50: =F49+D50-E50 -> 0 | M50: 其他负债 | N50: 递延税款贷项
A51: 46054 | F51: =F50+D51-E51 -> 0 | N51: 递延投资收益
A52: 46054 | F52: =F51+D52-E52 -> 0 | N52: 其他递延贷项
A53: 46054 | F53: =F52+D53-E53 -> 0 | M53: 所有者权益 | N53: 资本总额
A54: 46054 | F54: =F53+D54-E54 -> 0 | N54: 实收资本
A55: 46054 | F55: =F54+D55-E55 -> 0 | N55: 资本公积
A56: 46054 | F56: =F55+D56-E56 -> 0 | N56: 盈余公积
A57: 46054 | F57: =F56+D57-E57 -> 0 | N57: 本年利润
A58: 46054 | F58: =F57+D58-E58 -> 0 | N58: 未分配利润
A59: 46054 | F59: =F58+D59-E59 -> 0 | M59: 损益类 | N59: 产品（商品）销售收入
A60: 46054 | F60: =F59+D60-E60 -> 0 | N60: 服务收入
A61: 46054 | F61: =F60+D61-E61 -> 0 | N61: 主营业务成本
A62: 46054 | F62: =F61+D62-E62 -> 0 | N62: 主营业务税金及附加
A63: 46054 | F63: =F62+D63-E63 -> 0 | N63: 销售费用
A64: 46054 | F64: =F63+D64-E64 -> 0 | N64: 管理费用
A65: 46054 | F65: =F64+D65-E65 -> 0 | N65: 财务费用
A66: 46054 | F66: =F65+D66-E66 -> 0 | N66: 其他业务收入
A67: 46054 | F67: =F66+D67-E67 -> 0 | N67: 存货跌价损失
A68: 46054 | F68: =F67+D68-E68 -> 0 | N68: 投资收益
A69: 46054 | F69: =F68+D69-E69 -> 0 | N69: 补贴收入
A70: 46054 | F70: =F69+D70-E70 -> 0 | N70: 营业外收入
A71: 46054 | F71: =F70+D71-E71 -> 0 | N71: 营业外支出
... A74: 46054 | F74: =F73+D74-E74 -> 0 | N74: 净利润
A75: 46054 | F75: =F74+D75-E75 -> 0
A76: 46054 | F76: =F75+D76-E76 -> 0
A77: 46054 | F77: =F76+D77-E77 -> 0
A78: 46054 | F78: =F77+D78-E78 -> 0
A79: 46054 | F79: =F78+D79-E79 -> 0
A80: 46054 | F80: =F79+D80-E80 -> 0
A81: 46054 | F81: =F80+D81-E81 -> 0
A82: 46054 | F82: =F81+D82-E82 -> 0
A83: 46054 | F83: =F82+D83-E83 -> 0
A84: 46054 | F84: =F83+D84-E84 -> 0
A85: 46054 | F85: =F84+D85-E85 -> 0
A86: 46054 | F86: =F85+D86-E86 -> 0
... A162: 46054 | F162: =F161+D162-E162 -> 0

Sheet 原材料(加工用)
A1: 库存商品成本期末移动平均结转报告
A2: 编制单位：XXX公司 | I2: 报告日期：2026/2/1
A3: 库存货品名称及批次 | B3: 期初数 | D3: 采购入库 | G3: 耗用出库 | J3: 结存
B4: 数量 | C4: 总计金额 | D4: 数量 | E4: 单价 | F4: 采购金额 | G4: 数量 | H4: 加权平均单价 | I4: 出库金额 | J4: 剩余数量 | K4: 加权平均单价 | L4: 剩余总额
A5: asd | C5: =20*B5 -> 0 | L5: 0
F6: =D6*E6 -> 0 | G6: 0 | I6: =IF(F6=0,G6*H6,0) -> 0 | J6: =D6-G6+J5 -> 0 | K6: =IF(J6=0,0,L6/J6) -> 0 | L6: =IF(F6=0,L5-I6,L5+F6) -> 0
D7: 0 | E7: 0 | F7: =D7*E7 -> 0 | H7: =K6 -> 0 | I7: =IF(F7=0,G7*H7,0) -> 0 | J7: =D7-G7+J6 -> 0 | K7: =IF(J7=0,0,L7/J7) -> 0 | L7: =IF(F7=0,L6-I7,L6+F7) -> 0
D8: 20 | E8: 20.56 | F8: =D8*E8 -> 411.2 | G8: 0 | H8: =K7 -> 0 | I8: =IF(F8=0,G8*H8,0) -> 0 | J8: =D8-G8+J7 -> 20 | K8: =IF(J8=0,0,L8/J8) -> 20.56 | L8: =IF(F8=0,L7-I8,L7+F8) -> 411.2
D9: 20 | E9: 20.56 | F9: =D9*E9 -> 411.2 | G9: 0 | H9: =K8 -> 20.56 | I9: =IF(F9=0,G9*H9,0) -> 0 | J9: =D9-G9+J8 -> 40 | K9: =IF(J9=0,0,L9/J9) -> 20.56 | L9: =IF(F9=0,L8-I9,L8+F9) -> 822.4
D10: 20 | E10: 20.56 | F10: =D10*E10 -> 411.2 | G10: 0 | H10: =K9 -> 20.56 | I10: =IF(F10=0,G10*H10,0) -> 0 | J10: =D10-G10+J9 -> 60 | K10: =IF(J10=0,0,L10/J10) -> 20.56 | L10: =IF(F10=0,L9-I10,L9+F10) -> 1233.6
D11: 0 | F11: =D11*E11 -> 0 | G11: 0 | H11: =K10 -> 20.56 | I11: =IF(F11=0,G11*H11,0) -> 0 | J11: =D11-G11+J10 -> 60 | K11: =IF(J11=0,0,L11/J11) -> 20.56 | L11: =IF(F11=0,L10-I11,L10+F11) -> 1233.6
D12: 0 | F12: =D12*E12 -> 0 | G12: 0 | H12: =K8 -> 20.56 | I12: =IF(F12=0,G12*H12,0) -> 0 | J12: =D12-G12+J8 -> 20 | K12: =IF(J12=0,0,L12/J12) -> 20.56 | L12: =IF(F12=0,L8-I12,L8+F12) -> 411.2
D13: 0 | F13: =D13*E13 -> 0 | G13: 0 | H13: =K12 -> 20.56 | I13: =IF(F13=0,G13*H13,0) -> 0 | J13: =D13-G13+J12 -> 20 | K13: =IF(J13=0,0,L13/J13) -> 20.56 | L13: =IF(F13=0,L12-I13,L12+F13) -> 411.2
D14: 0 | F14: =D14*E14 -> 0 | G14: 0 | H14: =K13 -> 20.56 | I14: =IF(F14=0,G14*H14,0) -> 0 | J14: =D14-G14+J13 -> 20 | K14: =IF(J14=0,0,L14/J14) -> 20.56 | L14: =IF(F14=0,L13-I14,L13+F14) -> 411.2
D15: 0 | F15: =D15*E15 -> 0 | G15: 0 | H15: =K14 -> 20.56 | I15: =IF(F15=0,G15*H15,0) -> 0 | J15: =D15-G15+J14 -> 20 | K15: =IF(J15=0,0,L15/J15) -> 20.56 | L15: =IF(F15=0,L14-I15,L14+F15) -> 411.2
D16: 0 | F16: =D16*E16 -> 0 | G16: 0 | H16: =K15 -> 20.56 | I16: =IF(F16=0,G16*H16,0) -> 0 | J16: =D16-G16+J15 -> 20 | K16: =IF(J16=0,0,L16/J16) -> 20.56 | L16: =IF(F16=0,L15-I16,L15+F16) -> 411.2
D17: 0 | F17: =D17*E17 -> 0 | G17: 0 | H17: =K16 -> 20.56 | I17: =IF(F17=0,G17*H17,0) -> 0 | J17: =D17-G17+J16 -> 20 | K17: =IF(J17=0,0,L17/J17) -> 20.56 | L17: =IF(F17=0,L16-I17,L16+F17) -> 411.2
D18: 0 | F18: =D18*E18 -> 0 | G18: 0 | H18: =K17 -> 20.56 | I18: =IF(F18=0,G18*H18,0) -> 0 | J18: =D18-G18+J17 -> 20 | K18: =IF(J18=0,0,L18/J18) -> 20.56 | L18: =IF(F18=0,L17-I18,L17+F18) -> 411.2
D19: 0 | F19: =D19*E19 -> 0 | G19: 0 | H19: =K18 -> 20.56 | I19: =IF(F19=0,G19*H19,0) -> 0 | J19: =D19-G19+J18 -> 20 | K19: =IF(J19=0,0,L19/J19) -> 20.56 | L19: =IF(F19=0,L18-I19,L18+F19) -> 411.2
D20: 0 | F20: =D20*E20 -> 0 | G20: 0 | H20: =K19 -> 20.56 | I20: =IF(F20=0,G20*H20,0) -> 0 | J20: =D20-G20+J19 -> 20 | K20: =IF(J20=0,0,L20/J20) -> 20.56 | L20: =IF(F20=0,L19-I20,L19+F20) -> 411.2
F21: 本期采购入库 | G21: =SUM(F6:F20) -> 1233.6 | H21: 本期出库金额： | I21: =SUM(I6:I19) -> 0 | K21: 剩余总额 | L21: =L20 -> 411.2
A23: 库存商品成本期末移动平均结转报告
A24: 编制单位：XXX公司 | I24: 报告日期：2026/2/1
A25: 库存货品名称及批次 | B25: 期初数 | D25: 采购入库 | G25: 耗用出库 | J25: 结存
B26: 数量 | C26: 总计金额 | D26: 数量 | E26: 单价 | F26: 采购金额 | G26: 数量 | H26: 加权平均单价 | I26: 出库金额 | J26: 剩余数量 | K26: 加权平均单价 | L26: 剩余总额
A27: sadn | C27: =20*B27 -> 0 | L27: 0
D28: 0 | E28: 0 | F28: =D28*E28 -> 0 | G28: 0 | I28: =IF(F28=0,G28*H28,0) -> 0 | J28: =D28-G28+J27 -> 0 | K28: =IF(J28=0,0,L28/J28) -> 0 | L28: =IF(F28=0,L27-I28,L27+F28) -> 0
D29: 0 | F29: =D29*E29 -> 0 | G29: 10 | H29: =K28 -> 0 | I29: =IF(F29=0,G29*H29,0) -> 0 | J29: =D29-G29+J28 -> -10 | K29: =IF(J29=0,0,L29/J29) -> 0 | L29: =IF(F29=0,L28-I29,L28+F29) -> 0
D30: 0 | F30: =D30*E30 -> 0 | G30: 10 | H30: =K29 -> 0 | I30: =IF(F30=0,G30*H30,0) -> 0 | J30: =D30-G30+J29 -> -20 | K30: =IF(J30=0,0,L30/J30) -> 0 | L30: =IF(F30=0,L29-I30,L29+F30) -> 0
D31: 0 | F31: =D31*E31 -> 0 | G31: 0 | H31: =K30 -> 0 | I31: =IF(F31=0,G31*H31,0) -> 0 | J31: =D31-G31+J30 -> -20 | K31: =IF(J31=0,0,L31/J31) -> 0 | L31: =IF(F31=0,L30-I31,L30+F31) -> 0
D32: 0 | F32: =D32*E32 -> 0 | G32: 0 | H32: =K29 -> 0 | I32: =IF(F32=0,G32*H32,0) -> 0 | J32: =D32-G32+J29 -> -10 | K32: =IF(J32=0,0,L32/J32) -> 0 | L32: =IF(F32=0,L29-I32,L29+F32) -> 0
D33: 0 | F33: =D33*E33 -> 0 | G33: 0 | H33: =K32 -> 0 | I33: =IF(F33=0,G33*H33,0) -> 0 | J33: =D33-G33+J32 -> -10 | K33: =IF(J33=0,0,L33/J33) -> 0 | L33: =IF(F33=0,L32-I33,L32+F33) -> 0
D34: 0 | F34: =D34*E34 -> 0 | G34: 0 | H34: =K33 -> 0 | I34: =IF(F34=0,G34*H34,0) -> 0 | J34: =D34-G34+J33 -> -10 | K34: =IF(J34=0,0,L34/J34) -> 0 | L34: =IF(F34=0,L33-I34,L33+F34) -> 0
D35: 0 | F35: =D35*E35 -> 0 | G35: 0 | H35: =K34 -> 0 | I35: =IF(F35=0,G35*H35,0) -> 0 | J35: =D35-G35+J34 -> -10 | K35: =IF(J35=0,0,L35/J35) -> 0 | L35: =IF(F35=0,L34-I35,L34+F35) -> 0
D36: 0 | F36: =D36*E36 -> 0 | G36: 0 | H36: =K35 -> 0 | I36: =IF(F36=0,G36*H36,0) -> 0 | J36: =D36-G36+J35 -> -10 | K36: =IF(J36=0,0,L36/J36) -> 0 | L36: =IF(F36=0,L35-I36,L35+F36) -> 0
D37: 0 | F37: =D37*E37 -> 0 | G37: 0 | H37: =K36 -> 0 | I37: =IF(F37=0,G37*H37,0) -> 0 | J37: =D37-G37+J36 -> -10 | K37: =IF(J37=0,0,L37/J37) -> 0 | L37: =IF(F37=0,L36-I37,L36+F37) -> 0
D38: 0 | F38: =D38*E38 -> 0 | G38: 0 | H38: =K37 -> 0 | I38: =IF(F38=0,G38*H38,0) -> 0 | J38: =D38-G38+J37 -> -10 | K38: =IF(J38=0,0,L38/J38) -> 0 | L38: =IF(F38=0,L37-I38,L37+F38) -> 0
D39: 0 | F39: =D39*E39 -> 0 | G39: 0 | H39: =K38 -> 0 | I39: =IF(F39=0,G39*H39,0) -> 0 | J39: =D39-G39+J38 -> -10 | K39: =IF(J39=0,0,L39/J39) -> 0 | L39: =IF(F39=0,L38-I39,L38+F39) -> 0
D40: 0 | F40: =D40*E40 -> 0 | G40: 0 | H40: =K39 -> 0 | I40: =IF(F40=0,G40*H40,0) -> 0 | J40: =D40-G40+J39 -> -10 | K40: =IF(J40=0,0,L40/J40) -> 0 | L40: =IF(F40=0,L39-I40,L39+F40) -> 0
D41: 0 | F41: =D41*E41 -> 0 | G41: 0 | H41: =K40 -> 0 | I41: =IF(F41=0,G41*H41,0) -> 0 | J41: =D41-G41+J40 -> -10 | K41: =IF(J41=0,0,L41/J41) -> 0 | L41: =IF(F41=0,L40-I41,L40+F41) -> 0
F42: 本期采购入库 | G42: =SUM(F28:F41) -> 0 | H42: 本期出库金额： | I42: =SUM(I28:I40) -> 0 | K42: 剩余总额 | L42: =L41 -> 0
A45: 库存商品成本期末移动平均结转报告
A46: 编制单位：XXX公司 | I46: 报告日期：2026/2/1
A47: 库存货品名称及批次 | B47: 期初数 | D47: 采购入库 | G47: 耗用出库 | J47: 结存
B48: 数量 | C48: 总计金额 | D48: 数量 | E48: 单价 | F48: 采购金额 | G48: 数量 | H48: 加权平均单价 | I48: 出库金额 | J48: 剩余数量 | K48: 加权平均单价 | L48: 剩余总额
A49: ad | C49: =20*B49 -> 0 | L49: 0
D50: 0 | E50: 0 | F50: =D50*E50 -> 0 | G50: 0 | I50: =IF(F50=0,G50*H50,0) -> 0 | J50: =D50-G50+J49 -> 0 | K50: =IF(J50=0,0,L50/J50) -> 0 | L50: =IF(F50=0,L49-I50,L49+F50) -> 0
D51: 0 | F51: =D51*E51 -> 0 | G51: 0 | H51: =K50 -> 0 | I51: =IF(F51=0,G51*H51,0) -> 0 | J51: =D51-G51+J50 -> 0 | K51: =IF(J51=0,0,L51/J51) -> 0 | L51: =IF(F51=0,L50-I51,L50+F51) -> 0
D52: 0 | F52: =D52*E52 -> 0 | G52: 0 | H52: =K51 -> 0 | I52: =IF(F52=0,G52*H52,0) -> 0 | J52: =D52-G52+J51 -> 0 | K52: =IF(J52=0,0,L52/J52) -> 0 | L52: =IF(F52=0,L51-I52,L51+F52) -> 0
D53: 0 | F53: =D53*E53 -> 0 | G53: 0 | H53: =K52 -> 0 | I53: =IF(F53=0,G53*H53,0) -> 0 | J53: =D53-G53+J52 -> 0 | K53: =IF(J53=0,0,L53/J53) -> 0 | L53: =IF(F53=0,L52-I53,L52+F53) -> 0
D54: 0 | F54: =D54*E54 -> 0 | G54: 0 | H54: =K53 -> 0 | I54: =IF(F54=0,G54*H54,0) -> 0 | J54: =D54-G54+J53 -> 0 | K54: =IF(J54=0,0,L54/J54) -> 0 | L54: =IF(F54=0,L53-I54,L53+F54) -> 0
D55: 0 | F55: =D55*E55 -> 0 | G55: 0 | H55: =K54 -> 0 | I55: =IF(F55=0,G55*H55,0) -> 0 | J55: =D55-G55+J54 -> 0 | K55: =IF(J55=0,0,L55/J55) -> 0 | L55: =IF(F55=0,L54-I55,L54+F55) -> 0
D56: 0 | F56: =D56*E56 -> 0 | G56: 0 | H56: =K55 -> 0 | I56: =IF(F56=0,G56*H56,0) -> 0 | J56: =D56-G56+J55 -> 0 | K56: =IF(J56=0,0,L56/J56) -> 0 | L56: =IF(F56=0,L55-I56,L55+F56) -> 0
D57: 0 | F57: =D57*E57 -> 0 | G57: 0 | H57: =K56 -> 0 | I57: =IF(F57=0,G57*H57,0) -> 0 | J57: =D57-G57+J56 -> 0 | K57: =IF(J57=0,0,L57/J57) -> 0 | L57: =IF(F57=0,L56-I57,L56+F57) -> 0
D58: 0 | F58: =D58*E58 -> 0 | G58: 0 | H58: =K57 -> 0 | I58: =IF(F58=0,G58*H58,0) -> 0 | J58: =D58-G58+J57 -> 0 | K58: =IF(J58=0,0,L58/J58) -> 0 | L58: =IF(F58=0,L57-I58,L57+F58) -> 0
D59: 0 | F59: =D59*E59 -> 0 | G59: 0 | H59: =K58 -> 0 | I59: =IF(F59=0,G59*H59,0) -> 0 | J59: =D59-G59+J58 -> 0 | K59: =IF(J59=0,0,L59/J59) -> 0 | L59: =IF(F59=0,L58-I59,L58+F59) -> 0
D60: 0 | F60: =D60*E60 -> 0 | G60: 0 | H60: =K59 -> 0 | I60: =IF(F60=0,G60*H60,0) -> 0 | J60: =D60-G60+J59 -> 0 | K60: =IF(J60=0,0,L60/J60) -> 0 | L60: =IF(F60=0,L59-I60,L59+F60) -> 0
D61: 0 | F61: =D61*E61 -> 0 | G61: 0 | H61: =K60 -> 0 | I61: =IF(F61=0,G61*H61,0) -> 0 | J61: =D61-G61+J60 -> 0 | K61: =IF(J61=0,0,L61/J61) -> 0 | L61: =IF(F61=0,L60-I61,L60+F61) -> 0
F62: 本期采购入库 | G62: =SUM(F50:F61) -> 0 | H62: 本期出库金额： | I62: =SUM(I50:I60) -> 0 | K62: 剩余总额 | L62: =L61 -> 0
A65: 库存商品成本期末移动平均结转报告
A66: 编制单位：XXX公司 | I66: 报告日期：2026/2/1
A67: 库存货品名称及批次 | B67: 期初数 | D67: 采购入库 | G67: 耗用出库 | J67: 结存
B68: 数量 | C68: 总计金额 | D68: 数量 | E68: 单价 | F68: 采购金额 | G68: 数量 | H68: 加权平均单价 | I68: 出库金额 | J68: 剩余数量 | K68: 加权平均单价 | L68: 剩余总额
A69: qwe | C69: =20*B69 -> 0 | L69: 0
D70: 0 | E70: 0 | F70: =D70*E70 -> 0 | G70: 0 | I70: =IF(F70=0,G70*H70,0) -> 0 | J70: =D70-G70+J69 -> 0 | K70: =IF(J70=0,0,L70/J70) -> 0 | L70: =IF(F70=0,L69-I70,L69+F70) -> 0
D71: 0 | F71: =D71*E71 -> 0 | G71: 0 | H71: =K70 -> 0 | I71: =IF(F71=0,G71*H71,0) -> 0 | J71: =D71-G71+J70 -> 0 | K71: =IF(J71=0,0,L71/J71) -> 0 | L71: =IF(F71=0,L70-I71,L70+F71) -> 0
D72: 0 | F72: =D72*E72 -> 0 | G72: 0 | H72: =K71 -> 0 | I72: =IF(F72=0,G72*H72,0) -> 0 | J72: =D72-G72+J71 -> 0 | K72: =IF(J72=0,0,L72/J72) -> 0 | L72: =IF(F72=0,L71-I72,L71+F72) -> 0
D73: 0 | F73: =D73*E73 -> 0 | G73: 0 | H73: =K72 -> 0 | I73: =IF(F73=0,G73*H73,0) -> 0 | J73: =D73-G73+J72 -> 0 | K73: =IF(J73=0,0,L73/J73) -> 0 | L73: =IF(F73=0,L72-I73,L72+F73) -> 0
D74: 0 | F74: =D74*E74 -> 0 | G74: 0 | H74: =K73 -> 0 | I74: =IF(F74=0,G74*H74,0) -> 0 | J74: =D74-G74+J73 -> 0 | K74: =IF(J74=0,0,L74/J74) -> 0 | L74: =IF(F74=0,L73-I74,L73+F74) -> 0
D75: 0 | F75: =D75*E75 -> 0 | G75: 0 | H75: =K74 -> 0 | I75: =IF(F75=0,G75*H75,0) -> 0 | J75: =D75-G75+J74 -> 0 | K75: =IF(J75=0,0,L75/J75) -> 0 | L75: =IF(F75=0,L74-I75,L74+F75) -> 0
D76: 0 | F76: =D76*E76 -> 0 | G76: 0 | H76: =K75 -> 0 | I76: =IF(F76=0,G76*H76,0) -> 0 | J76: =D76-G76+J75 -> 0 | K76: =IF(J76=0,0,L76/J76) -> 0 | L76: =IF(F76=0,L75-I76,L75+F76) -> 0
D77: 0 | F77: =D77*E77 -> 0 | G77: 0 | H77: =K76 -> 0 | I77: =IF(F77=0,G77*H77,0) -> 0 | J77: =D77-G77+J76 -> 0 | K77: =IF(J77=0,0,L77/J77) -> 0 | L77: =IF(F77=0,L76-I77,L76+F77) -> 0
D78: 0 | F78: =D78*E78 -> 0 | G78: 0 | H78: =K77 -> 0 | I78: =IF(F78=0,G78*H78,0) -> 0 | J78: =D78-G78+J77 -> 0 | K78: =IF(J78=0,0,L78/J78) -> 0 | L78: =IF(F78=0,L77-I78,L77+F78) -> 0
D79: 0 | F79: =D79*E79 -> 0 | G79: 0 | H79: =K78 -> 0 | I79: =IF(F79=0,G79*H79,0) -> 0 | J79: =D79-G79+J78 -> 0 | K79: =IF(J79=0,0,L79/J79) -> 0 | L79: =IF(F79=0,L78-I79,L78+F79) -> 0
D80: 0 | F80: =D80*E80 -> 0 | G80: 0 | H80: =K79 -> 0 | I80: =IF(F80=0,G80*H80,0) -> 0 | J80: =D80-G80+J79 -> 0 | K80: =IF(J80=0,0,L80/J80) -> 0 | L80: =IF(F80=0,L79-I80,L79+F80) -> 0
D81: 0 | F81: =D81*E81 -> 0 | G81: 0 | H81: =K80 -> 0 | I81: =IF(F81=0,G81*H81,0) -> 0 | J81: =D81-G81+J80 -> 0 | K81: =IF(J81=0,0,L81/J81) -> 0 | L81: =IF(F81=0,L80-I81,L80+F81) -> 0
F82: 本期采购入库 | G82: =SUM(F70:F81) -> 0 | H82: 本期出库金额： | I82: =SUM(I70:I80) -> 0 | K82: 剩余总额 | L82: =L81 -> 0
A85: 库存商品成本期末移动平均结转报告
A86: 编制单位：XXX公司 | I86: 报告日期：2026/2/1
A87: 库存货品名称及批次 | B87: 期初数 | D87: 采购入库 | G87: 耗用出库 | J87: 结存
B88: 数量 | C88: 总计金额 | D88: 数量 | E88: 单价 | F88: 采购金额 | G88: 数量 | H88: 加权平均单价 | I88: 出库金额 | J88: 剩余数量 | K88: 加权平均单价 | L88: 剩余总额
A89: ew | C89: =20*B89 -> 0 | L89: 0
D90: 0 | E90: 0 | F90: =D90*E90 -> 0 | G90: 0 | I90: =IF(F90=0,G90*H90,0) -> 0 | J90: =D90-G90+J89 -> 0 | K90: =IF(J90=0,0,L90/J90) -> 0 | L90: =IF(F90=0,L89-I90,L89+F90) -> 0
D91: 0 | F91: =D91*E91 -> 0 | G91: 0 | H91: =K90 -> 0 | I91: =IF(F91=0,G91*H91,0) -> 0 | J91: =D91-G91+J90 -> 0 | K91: =IF(J91=0,0,L91/J91) -> 0 | L91: =IF(F91=0,L90-I91,L90+F91) -> 0
D92: 0 | F92: =D92*E92 -> 0 | G92: 0 | H92: =K91 -> 0 | I92: =IF(F92=0,G92*H92,0) -> 0 | J92: =D92-G92+J91 -> 0 | K92: =IF(J92=0,0,L92/J92) -> 0 | L92: =IF(F92=0,L91-I92,L91+F92) -> 0
D93: 0 | F93: =D93*E93 -> 0 | G93: 0 | H93: =K92 -> 0 | I93: =IF(F93=0,G93*H93,0) -> 0 | J93: =D93-G93+J92 -> 0 | K93: =IF(J93=0,0,L93/J93) -> 0 | L93: =IF(F93=0,L92-I93,L92+F93) -> 0
D94: 0 | F94: =D94*E94 -> 0 | G94: 0 | H94: =K93 -> 0 | I94: =IF(F94=0,G94*H94,0) -> 0 | J94: =D94-G94+J93 -> 0 | K94: =IF(J94=0,0,L94/J94) -> 0 | L94: =IF(F94=0,L93-I94,L93+F94) -> 0
D95: 0 | F95: =D95*E95 -> 0 | G95: 0 | H95: =K94 -> 0 | I95: =IF(F95=0,G95*H95,0) -> 0 | J95: =D95-G95+J94 -> 0 | K95: =IF(J95=0,0,L95/J95) -> 0 | L95: =IF(F95=0,L94-I95,L94+F95) -> 0
D96: 0 | F96: =D96*E96 -> 0 | G96: 0 | H96: =K95 -> 0 | I96: =IF(F96=0,G96*H96,0) -> 0 | J96: =D96-G96+J95 -> 0 | K96: =IF(J96=0,0,L96/J96) -> 0 | L96: =IF(F96=0,L95-I96,L95+F96) -> 0
D97: 0 | F97: =D97*E97 -> 0 | G97: 0 | H97: =K96 -> 0 | I97: =IF(F97=0,G97*H97,0) -> 0 | J97: =D97-G97+J96 -> 0 | K97: =IF(J97=0,0,L97/J97) -> 0 | L97: =IF(F97=0,L96-I97,L96+F97) -> 0
D98: 0 | F98: =D98*E98 -> 0 | G98: 0 | H98: =K97 -> 0 | I98: =IF(F98=0,G98*H98,0) -> 0 | J98: =D98-G98+J97 -> 0 | K98: =IF(J98=0,0,L98/J98) -> 0 | L98: =IF(F98=0,L97-I98,L97+F98) -> 0
D99: 0 | F99: =D99*E99 -> 0 | G99: 0 | H99: =K98 -> 0 | I99: =IF(F99=0,G99*H99,0) -> 0 | J99: =D99-G99+J98 -> 0 | K99: =IF(J99=0,0,L99/J99) -> 0 | L99: =IF(F99=0,L98-I99,L98+F99) -> 0
D100: 0 | F100: =D100*E100 -> 0 | G100: 0 | H100: =K99 -> 0 | I100: =IF(F100=0,G100*H100,0) -> 0 | J100: =D100-G100+J99 -> 0 | K100: =IF(J100=0,0,L100/J100) -> 0 | L100: =IF(F100=0,L99-I100,L99+F100) -> 0
D101: 0 | F101: =D101*E101 -> 0 | G101: 0 | H101: =K100 -> 0 | I101: =IF(F101=0,G101*H101,0) -> 0 | J101: =D101-G101+J100 -> 0 | K101: =IF(J101=0,0,L101/J101) -> 0 | L101: =IF(F101=0,L100-I101,L100+F101) -> 0
F102: 本期采购入库 | G102: =SUM(F90:F101) -> 0 | H102: 本期出库金额： | I102: =SUM(I90:I100) -> 0 | K102: 剩余总额 | L102: =L101 -> 0
A105: 库存商品成本期末移动平均结转报告
A106: 编制单位：XXX公司 | I106: 报告日期：2026/2/1
A107: 库存货品名称及批次 | B107: 期初数 | D107: 采购入库 | G107: 耗用出库 | J107: 结存
B108: 数量 | C108: 总计金额 | D108: 数量 | E108: 单价 | F108: 采购金额 | G108: 数量 | H108: 加权平均单价 | I108: 出库金额 | J108: 剩余数量 | K108: 加权平均单价 | L108: 剩余总额
A109: ry | C109: =20*B109 -> 0 | L109: 0
...

Sheet 零件（加工用）
A1: 库存商品成本期末移动平均结转报告
A2: 编制单位：XXX公司 | I2: 报告日期：2026/2/1
A3: 库存货品名称及批次 | B3: 期初数 | D3: 采购入库 | G3: 耗用出库 | J3: 结存
B4: 数量 | C4: 总计金额 | D4: 数量 | E4: 单价 | F4: 采购金额 | G4: 数量 | H4: 加权平均单价 | I4: 出库金额 | J4: 剩余数量 | K4: 加权平均单价 | L4: 剩余总额
A5: asd | C5: =20*B5 -> 0 | L5: 0
F6: =D6*E6 -> 0 | G6: 0 | I6: =IF(F6=0,G6*H6,0) -> 0 | J6: =D6-G6+J5 -> 0 | K6: =IF(J6=0,0,L6/J6) -> 0 | L6: =IF(F6=0,L5-I6,L5+F6) -> 0
D7: 20 | E7: 20.56 | F7: =D7*E7 -> 411.2 | G7: 0 | H7: =K6 -> 0 | I7: =IF(F7=0,G7*H7,0) -> 0 | J7: =D7-G7+J6 -> 20 | K7: =IF(J7=0,0,L7/J7) -> 20.56 | L7: =IF(F7=0,L6-I7,L6+F7) -> 411.2
D8: 20 | E8: 20.56 | F8: =D8*E8 -> 411.2 | G8: 0 | H8: =K7 -> 20.56 | I8: =IF(F8=0,G8*H8,0) -> 0 | J8: =D8-G8+J7 -> 40 | K8: =IF(J8=0,0,L8/J8) -> 20.56 | L8: =IF(F8=0,L7-I8,L7+F8) -> 822.4
D9: 0 | E9: 0 | F9: =D9*E9 -> 0 | G9: 0 | H9: =K8 -> 20.56 | I9: =IF(F9=0,G9*H9,0) -> 0 | J9: =D9-G9+J8 -> 40 | K9: =IF(J9=0,0,L9/J9) -> 20.56 | L9: =IF(F9=0,L8-I9,L8+F9) -> 822.4
D10: 0 | F10: =D10*E10 -> 0 | G10: 0 | H10: =K7 -> 20.56 | I10: =IF(F10=0,G10*H10,0) -> 0 | J10: =D10-G10+J7 -> 20 | K10: =IF(J10=0,0,L10/J10) -> 20.56 | L10: =IF(F10=0,L7-I10,L7+F10) -> 411.2
D11: 0 | F11: =D11*E11 -> 0 | G11: 0 | H11: =K10 -> 20.56 | I11: =IF(F11=0,G11*H11,0) -> 0 | J11: =D11-G11+J10 -> 20 | K11: =IF(J11=0,0,L11/J11) -> 20.56 | L11: =IF(F11=0,L10-I11,L10+F11) -> 411.2
D12: 0 | F12: =D12*E12 -> 0 | G12: 0 | H12: =K11 -> 20.56 | I12: =IF(F12=0,G12*H12,0) -> 0 | J12: =D12-G12+J11 -> 20 | K12: =IF(J12=0,0,L12/J12) -> 20.56 | L12: =IF(F12=0,L11-I12,L11+F12) -> 411.2
D13: 0 | F13: =D13*E13 -> 0 | G13: 0 | H13: =K12 -> 20.56 | I13: =IF(F13=0,G13*H13,0) -> 0 | J13: =D13-G13+J12 -> 20 | K13: =IF(J13=0,0,L13/J13) -> 20.56 | L13: =IF(F13=0,L12-I13,L12+F13) -> 411.2
D14: 0 | F14: =D14*E14 -> 0 | G14: 0 | H14: =K13 -> 20.56 | I14: =IF(F14=0,G14*H14,0) -> 0 | J14: =D14-G14+J13 -> 20 | K14: =IF(J14=0,0,L14/J14) -> 20.56 | L14: =IF(F14=0,L13-I14,L13+F14) -> 411.2
D15: 0 | F15: =D15*E15 -> 0 | G15: 0 | H15: =K14 -> 20.56 | I15: =IF(F15=0,G15*H15,0) -> 0 | J15: =D15-G15+J14 -> 20 | K15: =IF(J15=0,0,L15/J15) -> 20.56 | L15: =IF(F15=0,L14-I15,L14+F15) -> 411.2
D16: 0 | F16: =D16*E16 -> 0 | G16: 0 | H16: =K15 -> 20.56 | I16: =IF(F16=0,G16*H16,0) -> 0 | J16: =D16-G16+J15 -> 20 | K16: =IF(J16=0,0,L16/J16) -> 20.56 | L16: =IF(F16=0,L15-I16,L15+F16) -> 411.2
D17: 0 | F17: =D17*E17 -> 0 | G17: 0 | H17: =K16 -> 20.56 | I17: =IF(F17=0,G17*H17,0) -> 0 | J17: =D17-G17+J16 -> 20 | K17: =IF(J17=0,0,L17/J17) -> 20.56 | L17: =IF(F17=0,L16-I17,L16+F17) -> 411.2
D18: 0 | F18: =D18*E18 -> 0 | G18: 0 | H18: =K17 -> 20.56 | I18: =IF(F18=0,G18*H18,0) -> 0 | J18: =D18-G18+J17 -> 20 | K18: =IF(J18=0,0,L18/J18) -> 20.56 | L18: =IF(F18=0,L17-I18,L17+F18) -> 411.2
D19: 0 | F19: =D19*E19 -> 0 | G19: 0 | H19: =K18 -> 20.56 | I19: =IF(F19=0,G19*H19,0) -> 0 | J19: =D19-G19+J18 -> 20 | K19: =IF(J19=0,0,L19/J19) -> 20.56 | L19: =IF(F19=0,L18-I19,L18+F19) -> 411.2
F20: 本期采购入库 | G20: =SUM(F6:F19) -> 822.4 | H20: 本期出库金额： | I20: =SUM(I6:I18) -> 0 | K20: 剩余总额 | L20: =L19 -> 411.2
A22: 库存商品成本期末移动平均结转报告
A23: 编制单位：XXX公司 | I23: 报告日期：2026/2/1
A24: 库存货品名称及批次 | B24: 期初数 | D24: 采购入库 | G24: 耗用出库 | J24: 结存
B25: 数量 | C25: 总计金额 | D25: 数量 | E25: 单价 | F25: 采购金额 | G25: 数量 | H25: 加权平均单价 | I25: 出库金额 | J25: 剩余数量 | K25: 加权平均单价 | L25: 剩余总额
A26: sadn | C26: =20*B26 -> 0 | L26: 0
D27: 0 | E27: 0 | F27: =D27*E27 -> 0 | G27: 0 | I27: =IF(F27=0,G27*H27,0) -> 0 | J27: =D27-G27+J26 -> 0 | K27: =IF(J27=0,0,L27/J27) -> 0 | L27: =IF(F27=0,L26-I27,L26+F27) -> 0
D28: 0 | F28: =D28*E28 -> 0 | G28: 10 | H28: =K27 -> 0 | I28: =IF(F28=0,G28*H28,0) -> 0 | J28: =D28-G28+J27 -> -10 | K28: =IF(J28=0,0,L28/J28) -> 0 | L28: =IF(F28=0,L27-I28,L27+F28) -> 0
D29: 0 | F29: =D29*E29 -> 0 | G29: 10 | H29: =K28 -> 0 | I29: =IF(F29=0,G29*H29,0) -> 0 | J29: =D29-G29+J28 -> -20 | K29: =IF(J29=0,0,L29/J29) -> 0 | L29: =IF(F29=0,L28-I29,L28+F29) -> 0
D30: 0 | F30: =D30*E30 -> 0 | G30: 0 | H30: =K29 -> 0 | I30: =IF(F30=0,G30*H30,0) -> 0 | J30: =D30-G30+J29 -> -20 | K30: =IF(J30=0,0,L30/J30) -> 0 | L30: =IF(F30=0,L29-I30,L29+F30) -> 0
D31: 0 | F31: =D31*E31 -> 0 | G31: 0 | H31: =K28 -> 0 | I31: =IF(F31=0,G31*H31,0) -> 0 | J31: =D31-G31+J28 -> -10 | K31: =IF(J31=0,0,L31/J31) -> 0 | L31: =IF(F31=0,L28-I31,L28+F31) -> 0
D32: 0 | F32: =D32*E32 -> 0 | G32: 0 | H32: =K31 -> 0 | I32: =IF(F32=0,G32*H32,0) -> 0 | J32: =D32-G32+J31 -> -10 | K32: =IF(J32=0,0,L32/J32) -> 0 | L32: =IF(F32=0,L31-I32,L31+F32) -> 0
D33: 0 | F33: =D33*E33 -> 0 | G33: 0 | H33: =K32 -> 0 | I33: =IF(F33=0,G33*H33,0) -> 0 | J33: =D33-G33+J32 -> -10 | K33: =IF(J33=0,0,L33/J33) -> 0 | L33: =IF(F33=0,L32-I33,L32+F33) -> 0
D34: 0 | F34: =D34*E34 -> 0 | G34: 0 | H34: =K33 -> 0 | I34: =IF(F34=0,G34*H34,0) -> 0 | J34: =D34-G34+J33 -> -10 | K34: =IF(J34=0,0,L34/J34) -> 0 | L34: =IF(F34=0,L33-I34,L33+F34) -> 0
D35: 0 | F35: =D35*E35 -> 0 | G35: 0 | H35: =K34 -> 0 | I35: =IF(F35=0,G35*H35,0) -> 0 | J35: =D35-G35+J34 -> -10 | K35: =IF(J35=0,0,L35/J35) -> 0 | L35: =IF(F35=0,L34-I35,L34+F35) -> 0
D36: 0 | F36: =D36*E36 -> 0 | G36: 0 | H36: =K35 -> 0 | I36: =IF(F36=0,G36*H36,0) -> 0 | J36: =D36-G36+J35 -> -10 | K36: =IF(J36=0,0,L36/J36) -> 0 | L36: =IF(F36=0,L35-I36,L35+F36) -> 0
D37: 0 | F37: =D37*E37 -> 0 | G37: 0 | H37: =K36 -> 0 | I37: =IF(F37=0,G37*H37,0) -> 0 | J37: =D37-G37+J36 -> -10 | K37: =IF(J37=0,0,L37/J37) -> 0 | L37: =IF(F37=0,L36-I37,L36+F37) -> 0
D38: 0 | F38: =D38*E38 -> 0 | G38: 0 | H38: =K37 -> 0 | I38: =IF(F38=0,G38*H38,0) -> 0 | J38: =D38-G38+J37 -> -10 | K38: =IF(J38=0,0,L38/J38) -> 0 | L38: =IF(F38=0,L37-I38,L37+F38) -> 0
D39: 0 | F39: =D39*E39 -> 0 | G39: 0 | H39: =K38 -> 0 | I39: =IF(F39=0,G39*H39,0) -> 0 | J39: =D39-G39+J38 -> -10 | K39: =IF(J39=0,0,L39/J39) -> 0 | L39: =IF(F39=0,L38-I39,L38+F39) -> 0
D40: 0 | F40: =D40*E40 -> 0 | G40: 0 | H40: =K39 -> 0 | I40: =IF(F40=0,G40*H40,0) -> 0 | J40: =D40-G40+J39 -> -10 | K40: =IF(J40=0,0,L40/J40) -> 0 | L40: =IF(F40=0,L39-I40,L39+F40) -> 0
F41: 本期采购入库 | G41: =SUM(F27:F40) -> 0 | H41: 本期出库金额： | I41: =SUM(I27:I39) -> 0 | K41: 剩余总额 | L41: =L40 -> 0
A44: 库存商品成本期末移动平均结转报告
A45: 编制单位：XXX公司 | I45: 报告日期：2026/2/1
A46: 库存货品名称及批次 | B46: 期初数 | D46: 采购入库 | G46: 耗用出库 | J46: 结存
B47: 数量 | C47: 总计金额 | D47: 数量 | E47: 单价 | F47: 采购金额 | G47: 数量 | H47: 加权平均单价 | I47: 出库金额 | J47: 剩余数量 | K47: 加权平均单价 | L47: 剩余总额
C48: =20*B48 -> 0 | L48: 0
D49: 0 | E49: 0 | F49: =D49*E49 -> 0 | G49: 0 | I49: =IF(F49=0,G49*H49,0) -> 0 | J49: =D49-G49+J48 -> 0 | K49: =IF(J49=0,0,L49/J49) -> 0 | L49: =IF(F49=0,L48-I49,L48+F49) -> 0
D50: 0 | F50: =D50*E50 -> 0 | G50: 0 | H50: =K49 -> 0 | I50: =IF(F50=0,G50*H50,0) -> 0 | J50: =D50-G50+J49 -> 0 | K50: =IF(J50=0,0,L50/J50) -> 0 | L50: =IF(F50=0,L49-I50,L49+F50) -> 0
D51: 0 | F51: =D51*E51 -> 0 | G51: 0 | H51: =K50 -> 0 | I51: =IF(F51=0,G51*H51,0) -> 0 | J51: =D51-G51+J50 -> 0 | K51: =IF(J51=0,0,L51/J51) -> 0 | L51: =IF(F51=0,L50-I51,L50+F51) -> 0
D52: 0 | F52: =D52*E52 -> 0 | G52: 0 | H52: =K51 -> 0 | I52: =IF(F52=0,G52*H52,0) -> 0 | J52: =D52-G52+J51 -> 0 | K52: =IF(J52=0,0,L52/J52) -> 0 | L52: =IF(F52=0,L51-I52,L51+F52) -> 0
D53: 0 | F53: =D53*E53 -> 0 | G53: 0 | H53: =K52 -> 0 | I53: =IF(F53=0,G53*H53,0) -> 0 | J53: =D53-G53+J52 -> 0 | K53: =IF(J53=0,0,L53/J53) -> 0 | L53: =IF(F53=0,L52-I53,L52+F53) -> 0
D54: 0 | F54: =D54*E54 -> 0 | G54: 0 | H54: =K53 -> 0 | I54: =IF(F54=0,G54*H54,0) -> 0 | J54: =D54-G54+J53 -> 0 | K54: =IF(J54=0,0,L54/J54) -> 0 | L54: =IF(F54=0,L53-I54,L53+F54) -> 0
D55: 0 | F55: =D55*E55 -> 0 | G55: 0 | H55: =K54 -> 0 | I55: =IF(F55=0,G55*H55,0) -> 0 | J55: =D55-G55+J54 -> 0 | K55: =IF(J55=0,0,L55/J55) -> 0 | L55: =IF(F55=0,L54-I55,L54+F55) -> 0
D56: 0 | F56: =D56*E56 -> 0 | G56: 0 | H56: =K55 -> 0 | I56: =IF(F56=0,G56*H56,0) -> 0 | J56: =D56-G56+J55 -> 0 | K56: =IF(J56=0,0,L56/J56) -> 0 | L56: =IF(F56=0,L55-I56,L55+F56) -> 0
D57: 0 | F57: =D57*E57 -> 0 | G57: 0 | H57: =K56 -> 0 | I57: =IF(F57=0,G57*H57,0) -> 0 | J57: =D57-G57+J56 -> 0 | K57: =IF(J57=0,0,L57/J57) -> 0 | L57: =IF(F57=0,L56-I57,L56+F57) -> 0
D58: 0 | F58: =D58*E58 -> 0 | G58: 0 | H58: =K57 -> 0 | I58: =IF(F58=0,G58*H58,0) -> 0 | J58: =D58-G58+J57 -> 0 | K58: =IF(J58=0,0,L58/J58) -> 0 | L58: =IF(F58=0,L57-I58,L57+F58) -> 0
D59: 0 | F59: =D59*E59 -> 0 | G59: 0 | H59: =K58 -> 0 | I59: =IF(F59=0,G59*H59,0) -> 0 | J59: =D59-G59+J58 -> 0 | K59: =IF(J59=0,0,L59/J59) -> 0 | L59: =IF(F59=0,L58-I59,L58+F59) -> 0
D60: 0 | F60: =D60*E60 -> 0 | G60: 0 | H60: =K59 -> 0 | I60: =IF(F60=0,G60*H60,0) -> 0 | J60: =D60-G60+J59 -> 0 | K60: =IF(J60=0,0,L60/J60) -> 0 | L60: =IF(F60=0,L59-I60,L59+F60) -> 0
F61: 本期采购入库 | G61: =SUM(F49:F60) -> 0 | H61: 本期出库金额： | I61: =SUM(I49:I59) -> 0 | K61: 剩余总额 | L61: =L60 -> 0
A64: 库存商品成本期末移动平均结转报告
A65: 编制单位：XXX公司 | I65: 报告日期：2026/2/1
A66: 库存货品名称及批次 | B66: 期初数 | D66: 采购入库 | G66: 耗用出库 | J66: 结存
B67: 数量 | C67: 总计金额 | D67: 数量 | E67: 单价 | F67: 采购金额 | G67: 数量 | H67: 加权平均单价 | I67: 出库金额 | J67: 剩余数量 | K67: 加权平均单价 | L67: 剩余总额
C68: =20*B68 -> 0 | L68: 0
D69: 0 | E69: 0 | F69: =D69*E69 -> 0 | G69: 0 | I69: =IF(F69=0,G69*H69,0) -> 0 | J69: =D69-G69+J68 -> 0 | K69: =IF(J69=0,0,L69/J69) -> 0 | L69: =IF(F69=0,L68-I69,L68+F69) -> 0
D70: 0 | F70: =D70*E70 -> 0 | G70: 0 | H70: =K69 -> 0 | I70: =IF(F70=0,G70*H70,0) -> 0 | J70: =D70-G70+J69 -> 0 | K70: =IF(J70=0,0,L70/J70) -> 0 | L70: =IF(F70=0,L69-I70,L69+F70) -> 0
D71: 0 | F71: =D71*E71 -> 0 | G71: 0 | H71: =K70 -> 0 | I71: =IF(F71=0,G71*H71,0) -> 0 | J71: =D71-G71+J70 -> 0 | K71: =IF(J71=0,0,L71/J71) -> 0 | L71: =IF(F71=0,L70-I71,L70+F71) -> 0
D72: 0 | F72: =D72*E72 -> 0 | G72: 0 | H72: =K71 -> 0 | I72: =IF(F72=0,G72*H72,0) -> 0 | J72: =D72-G72+J71 -> 0 | K72: =IF(J72=0,0,L72/J72) -> 0 | L72: =IF(F72=0,L71-I72,L71+F72) -> 0
D73: 0 | F73: =D73*E73 -> 0 | G73: 0 | H73: =K72 -> 0 | I73: =IF(F73=0,G73*H73,0) -> 0 | J73: =D73-G73+J72 -> 0 | K73: =IF(J73=0,0,L73/J73) -> 0 | L73: =IF(F73=0,L72-I73,L72+F73) -> 0
D74: 0 | F74: =D74*E74 -> 0 | G74: 0 | H74: =K73 -> 0 | I74: =IF(F74=0,G74*H74,0) -> 0 | J74: =D74-G74+J73 -> 0 | K74: =IF(J74=0,0,L74/J74) -> 0 | L74: =IF(F74=0,L73-I74,L73+F74) -> 0
D75: 0 | F75: =D75*E75 -> 0 | G75: 0 | H75: =K74 -> 0 | I75: =IF(F75=0,G75*H75,0) -> 0 | J75: =D75-G75+J74 -> 0 | K75: =IF(J75=0,0,L75/J75) -> 0 | L75: =IF(F75=0,L74-I75,L74+F75) -> 0
D76: 0 | F76: =D76*E76 -> 0 | G76: 0 | H76: =K75 -> 0 | I76: =IF(F76=0,G76*H76,0) -> 0 | J76: =D76-G76+J75 -> 0 | K76: =IF(J76=0,0,L76/J76) -> 0 | L76: =IF(F76=0,L75-I76,L75+F76) -> 0
D77: 0 | F77: =D77*E77 -> 0 | G77: 0 | H77: =K76 -> 0 | I77: =IF(F77=0,G77*H77,0) -> 0 | J77: =D77-G77+J76 -> 0 | K77: =IF(J77=0,0,L77/J77) -> 0 | L77: =IF(F77=0,L76-I77,L76+F77) -> 0
D78: 0 | F78: =D78*E78 -> 0 | G78: 0 | H78: =K77 -> 0 | I78: =IF(F78=0,G78*H78,0) -> 0 | J78: =D78-G78+J77 -> 0 | K78: =IF(J78=0,0,L78/J78) -> 0 | L78: =IF(F78=0,L77-I78,L77+F78) -> 0
D79: 0 | F79: =D79*E79 -> 0 | G79: 0 | H79: =K78 -> 0 | I79: =IF(F79=0,G79*H79,0) -> 0 | J79: =D79-G79+J78 -> 0 | K79: =IF(J79=0,0,L79/J79) -> 0 | L79: =IF(F79=0,L78-I79,L78+F79) -> 0
D80: 0 | F80: =D80*E80 -> 0 | G80: 0 | H80: =K79 -> 0 | I80: =IF(F80=0,G80*H80,0) -> 0 | J80: =D80-G80+J79 -> 0 | K80: =IF(J80=0,0,L80/J80) -> 0 | L80: =IF(F80=0,L79-I80,L79+F80) -> 0
F81: 本期采购入库 | G81: =SUM(F69:F80) -> 0 | H81: 本期出库金额： | I81: =SUM(I69:I79) -> 0 | K81: 剩余总额 | L81: =L80 -> 0
A84: 库存商品成本期末移动平均结转报告
A85: 编制单位：XXX公司 | I85: 报告日期：2026/2/1
A86: 库存货品名称及批次 | B86: 期初数 | D86: 采购入库 | G86: 耗用出库 | J86: 结存
B87: 数量 | C87: 总计金额 | D87: 数量 | E87: 单价 | F87: 采购金额 | G87: 数量 | H87: 加权平均单价 | I87: 出库金额 | J87: 剩余数量 | K87: 加权平均单价 | L87: 剩余总额
C88: =20*B88 -> 0 | L88: 0
D89: 0 | E89: 0 | F89: =D89*E89 -> 0 | G89: 0 | I89: =IF(F89=0,G89*H89,0) -> 0 | J89: =D89-G89+J88 -> 0 | K89: =IF(J89=0,0,L89/J89) -> 0 | L89: =IF(F89=0,L88-I89,L88+F89) -> 0
D90: 0 | F90: =D90*E90 -> 0 | G90: 0 | H90: =K89 -> 0 | I90: =IF(F90=0,G90*H90,0) -> 0 | J90: =D90-G90+J89 -> 0 | K90: =IF(J90=0,0,L90/J90) -> 0 | L90: =IF(F90=0,L89-I90,L89+F90) -> 0
D91: 0 | F91: =D91*E91 -> 0 | G91: 0 | H91: =K90 -> 0 | I91: =IF(F91=0,G91*H91,0) -> 0 | J91: =D91-G91+J90 -> 0 | K91: =IF(J91=0,0,L91/J91) -> 0 | L91: =IF(F91=0,L90-I91,L90+F91) -> 0
D92: 0 | F92: =D92*E92 -> 0 | G92: 0 | H92: =K91 -> 0 | I92: =IF(F92=0,G92*H92,0) -> 0 | J92: =D92-G92+J91 -> 0 | K92: =IF(J92=0,0,L92/J92) -> 0 | L92: =IF(F92=0,L91-I92,L91+F92) -> 0
D93: 0 | F93: =D93*E93 -> 0 | G93: 0 | H93: =K92 -> 0 | I93: =IF(F93=0,G93*H93,0) -> 0 | J93: =D93-G93+J92 -> 0 | K93: =IF(J93=0,0,L93/J93) -> 0 | L93: =IF(F93=0,L92-I93,L92+F93) -> 0
D94: 0 | F94: =D94*E94 -> 0 | G94: 0 | H94: =K93 -> 0 | I94: =IF(F94=0,G94*H94,0) -> 0 | J94: =D94-G94+J93 -> 0 | K94: =IF(J94=0,0,L94/J94) -> 0 | L94: =IF(F94=0,L93-I94,L93+F94) -> 0
D95: 0 | F95: =D95*E95 -> 0 | G95: 0 | H95: =K94 -> 0 | I95: =IF(F95=0,G95*H95,0) -> 0 | J95: =D95-G95+J94 -> 0 | K95: =IF(J95=0,0,L95/J95) -> 0 | L95: =IF(F95=0,L94-I95,L94+F95) -> 0
D96: 0 | F96: =D96*E96 -> 0 | G96: 0 | H96: =K95 -> 0 | I96: =IF(F96=0,G96*H96,0) -> 0 | J96: =D96-G96+J95 -> 0 | K96: =IF(J96=0,0,L96/J96) -> 0 | L96: =IF(F96=0,L95-I96,L95+F96) -> 0
D97: 0 | F97: =D97*E97 -> 0 | G97: 0 | H97: =K96 -> 0 | I97: =IF(F97=0,G97*H97,0) -> 0 | J97: =D97-G97+J96 -> 0 | K97: =IF(J97=0,0,L97/J97) -> 0 | L97: =IF(F97=0,L96-I97,L96+F97) -> 0
D98: 0 | F98: =D98*E98 -> 0 | G98: 0 | H98: =K97 -> 0 | I98: =IF(F98=0,G98*H98,0) -> 0 | J98: =D98-G98+J97 -> 0 | K98: =IF(J98=0,0,L98/J98) -> 0 | L98: =IF(F98=0,L97-I98,L97+F98) -> 0
D99: 0 | F99: =D99*E99 -> 0 | G99: 0 | H99: =K98 -> 0 | I99: =IF(F99=0,G99*H99,0) -> 0 | J99: =D99-G99+J98 -> 0 | K99: =IF(J99=0,0,L99/J99) -> 0 | L99: =IF(F99=0,L98-I99,L98+F99) -> 0
D100: 0 | F100: =D100*E100 -> 0 | G100: 0 | H100: =K99 -> 0 | I100: =IF(F100=0,G100*H100,0) -> 0 | J100: =D100-G100+J99 -> 0 | K100: =IF(J100=0,0,L100/J100) -> 0 | L100: =IF(F100=0,L99-I100,L99+F100) -> 0
F101: 本期采购入库 | G101: =SUM(F89:F100) -> 0 | H101: 本期出库金额： | I101: =SUM(I89:I99) -> 0 | K101: 剩余总额 | L101: =L100 -> 0
A104: 库存商品成本期末移动平均结转报告
A105: 编制单位：XXX公司 | I105: 报告日期：2026/2/1
A106: 库存货品名称及批次 | B106: 期初数 | D106: 采购入库 | G106: 耗用出库 | J106: 结存
B107: 数量 | C107: 总计金额 | D107: 数量 | E107: 单价 | F107: 采购金额 | G107: 数量 | H107: 加权平均单价 | I107: 出库金额 | J107: 剩余数量 | K107: 加权平均单价 | L107: 剩余总额
C108: =20*B108 -> 0 | L108: 0
D109: 0 | E109: 0 | F109: =D109*E109 -> 0 | G109: 0 | I109: =IF(F109=0,G109*H109,0) -> 0 | J109: =D109-G109+J108 -> 0 | K109: =IF(J109=0,0,L109/J109) -> 0 | L109: =IF(F109=0,L108-I109,L108+F109) -> 0
...

Sheet 商品（各实体用）
A1: 库存商品成本期末移动平均结转报告
A2: 编制单位：XXX公司 | I2: 报告日期：2026/2/1
A3: 库存货品名称及批次 | B3: 期初数 | D3: 采购入库 | G3: 耗用出库 | J3: 结存
B4: 数量 | C4: 总计金额 | D4: 数量 | E4: 单价 | F4: 采购金额 | G4: 数量 | H4: 加权平均单价 | I4: 出库金额 | J4: 剩余数量 | K4: 加权平均单价 | L4: 剩余总额
A5: asd | C5: =20*B5 -> 0 | L5: 0
E6: =IF(D6=0,0,F6/D6) -> 0 | G6: 0 | I6: =IF(F6=0,G6*H6,0) -> 0 | J6: =D6-G6+J5 -> 0 | K6: =IF(J6=0,0,L6/J6) -> 0 | L6: =IF(F6=0,L5-I6,L5+F6) -> 0
D7: 20 | E7: =IF(D7=0,0,F7/D7) -> 1.028 | F7: 20.56 | G7: 0 | H7: =K6 -> 0 | I7: =IF(F7=0,G7*H7,0) -> 0 | J7: =D7-G7+J6 -> 20 | K7: =IF(J7=0,0,L7/J7) -> 1.028 | L7: =IF(F7=0,L6-I7,L6+F7) -> 20.56
D8: 20 | E8: =IF(D8=0,0,F8/D8) -> 1.028 | F8: 20.56 | G8: 0 | H8: =K7 -> 1.028 | I8: =IF(F8=0,G8*H8,0) -> 0 | J8: =D8-G8+J7 -> 40 | K8: =IF(J8=0,0,L8/J8) -> 1.028 | L8: =IF(F8=0,L7-I8,L7+F8) -> 41.12
D9: 0 | E9: =IF(D9=0,0,F9/D9) -> 0 | F9: 0 | G9: 0 | H9: =K8 -> 1.028 | I9: =IF(F9=0,G9*H9,0) -> 0 | J9: =D9-G9+J8 -> 40 | K9: =IF(J9=0,0,L9/J9) -> 1.028 | L9: =IF(F9=0,L8-I9,L8+F9) -> 41.12
D10: 0 | E10: =IF(D10=0,0,F10/D10) -> 0 | F10: 0 | G10: 0 | H10: =K7 -> 1.028 | I10: =IF(F10=0,G10*H10,0) -> 0 | J10: =D10-G10+J7 -> 20 | K10: =IF(J10=0,0,L10/J10) -> 1.028 | L10: =IF(F10=0,L7-I10,L7+F10) -> 20.56
D11: 0 | E11: =IF(D11=0,0,F11/D11) -> 0 | F11: 0 | G11: 0 | H11: =K10 -> 1.028 | I11: =IF(F11=0,G11*H11,0) -> 0 | J11: =D11-G11+J10 -> 20 | K11: =IF(J11=0,0,L11/J11) -> 1.028 | L11: =IF(F11=0,L10-I11,L10+F11) -> 20.56
D12: 0 | E12: =IF(D12=0,0,F12/D12) -> 0 | F12: 0 | G12: 0 | H12: =K11 -> 1.028 | I12: =IF(F12=0,G12*H12,0) -> 0 | J12: =D12-G12+J11 -> 20 | K12: =IF(J12=0,0,L12/J12) -> 1.028 | L12: =IF(F12=0,L11-I12,L11+F12) -> 20.56
D13: 0 | E13: =IF(D13=0,0,F13/D13) -> 0 | F13: 0 | G13: 0 | H13: =K12 -> 1.028 | I13: =IF(F13=0,G13*H13,0) -> 0 | J13: =D13-G13+J12 -> 20 | K13: =IF(J13=0,0,L13/J13) -> 1.028 | L13: =IF(F13=0,L12-I13,L12+F13) -> 20.56
D14: 0 | E14: =IF(D14=0,0,F14/D14) -> 0 | F14: 0 | G14: 0 | H14: =K13 -> 1.028 | I14: =IF(F14=0,G14*H14,0) -> 0 | J14: =D14-G14+J13 -> 20 | K14: =IF(J14=0,0,L14/J14) -> 1.028 | L14: =IF(F14=0,L13-I14,L13+F14) -> 20.56
D15: 0 | E15: =IF(D15=0,0,F15/D15) -> 0 | F15: 0 | G15: 0 | H15: =K14 -> 1.028 | I15: =IF(F15=0,G15*H15,0) -> 0 | J15: =D15-G15+J14 -> 20 | K15: =IF(J15=0,0,L15/J15) -> 1.028 | L15: =IF(F15=0,L14-I15,L14+F15) -> 20.56
D16: 0 | E16: =IF(D16=0,0,F16/D16) -> 0 | F16: 0 | G16: 0 | H16: =K15 -> 1.028 | I16: =IF(F16=0,G16*H16,0) -> 0 | J16: =D16-G16+J15 -> 20 | K16: =IF(J16=0,0,L16/J16) -> 1.028 | L16: =IF(F16=0,L15-I16,L15+F16) -> 20.56
D17: 0 | E17: =IF(D17=0,0,F17/D17) -> 0 | F17: 0 | G17: 0 | H17: =K16 -> 1.028 | I17: =IF(F17=0,G17*H17,0) -> 0 | J17: =D17-G17+J16 -> 20 | K17: =IF(J17=0,0,L17/J17) -> 1.028 | L17: =IF(F17=0,L16-I17,L16+F17) -> 20.56
D18: 0 | E18: =IF(D18=0,0,F18/D18) -> 0 | F18: 0 | G18: 0 | H18: =K17 -> 1.028 | I18: =IF(F18=0,G18*H18,0) -> 0 | J18: =D18-G18+J17 -> 20 | K18: =IF(J18=0,0,L18/J18) -> 1.028 | L18: =IF(F18=0,L17-I18,L17+F18) -> 20.56
D19: 0 | E19: =IF(D19=0,0,F19/D19) -> 0 | F19: 0 | G19: 0 | H19: =K18 -> 1.028 | I19: =IF(F19=0,G19*H19,0) -> 0 | J19: =D19-G19+J18 -> 20 | K19: =IF(J19=0,0,L19/J19) -> 1.028 | L19: =IF(F19=0,L18-I19,L18+F19) -> 20.56
F20: 本期采购入库 | G20: =SUM(F6:F19) -> 41.12 | H20: 本期出库金额： | I20: =SUM(I6:I19) -> 0 | K20: 剩余总额 | L20: =L19 -> 20.56
A22: 库存商品成本期末移动平均结转报告
A23: 编制单位：XXX公司 | I23: 报告日期：2026/2/1
A24: 库存货品名称及批次 | B24: 期初数 | D24: 采购入库 | G24: 耗用出库 | J24: 结存
B25: 数量 | C25: 总计金额 | D25: 数量 | E25: 单价 | F25: 采购金额 | G25: 数量 | H25: 加权平均单价 | I25: 出库金额 | J25: 剩余数量 | K25: 加权平均单价 | L25: 剩余总额
A26: sadn | C26: =20*B26 -> 0 | L26: 0
D27: 0 | E27: =IF(D27=0,0,F27/D27) -> 0 | F27: 0 | G27: 0 | I27: =IF(F27=0,G27*H27,0) -> 0 | J27: =D27-G27+J26 -> 0 | K27: =IF(J27=0,0,L27/J27) -> 0 | L27: =IF(F27=0,L26-I27,L26+F27) -> 0
D28: 0 | E28: =IF(D28=0,0,F28/D28) -> 0 | F28: 0 | G28: 10 | H28: =K27 -> 0 | I28: =IF(F28=0,G28*H28,0) -> 0 | J28: =D28-G28+J27 -> -10 | K28: =IF(J28=0,0,L28/J28) -> 0 | L28: =IF(F28=0,L27-I28,L27+F28) -> 0
D29: 0 | E29: =IF(D29=0,0,F29/D29) -> 0 | F29: 0 | G29: 10 | H29: =K28 -> 0 | I29: =IF(F29=0,G29*H29,0) -> 0 | J29: =D29-G29+J28 -> -20 | K29: =IF(J29=0,0,L29/J29) -> 0 | L29: =IF(F29=0,L28-I29,L28+F29) -> 0
D30: 0 | E30: =IF(D30=0,0,F30/D30) -> 0 | F30: 0 | G30: 0 | H30: =K29 -> 0 | I30: =IF(F30=0,G30*H30,0) -> 0 | J30: =D30-G30+J29 -> -20 | K30: =IF(J30=0,0,L30/J30) -> 0 | L30: =IF(F30=0,L29-I30,L29+F30) -> 0
D31: 0 | E31: =IF(D31=0,0,F31/D31) -> 0 | F31: 0 | G31: 0 | H31: =K28 -> 0 | I31: =IF(F31=0,G31*H31,0) -> 0 | J31: =D31-G31+J28 -> -10 | K31: =IF(J31=0,0,L31/J31) -> 0 | L31: =IF(F31=0,L28-I31,L28+F31) -> 0
D32: 0 | E32: =IF(D32=0,0,F32/D32) -> 0 | F32: 0 | G32: 0 | H32: =K31 -> 0 | I32: =IF(F32=0,G32*H32,0) -> 0 | J32: =D32-G32+J31 -> -10 | K32: =IF(J32=0,0,L32/J32) -> 0 | L32: =IF(F32=0,L31-I32,L31+F32) -> 0
D33: 0 | E33: =IF(D33=0,0,F33/D33) -> 0 | F33: 0 | G33: 0 | H33: =K32 -> 0 | I33: =IF(F33=0,G33*H33,0) -> 0 | J33: =D33-G33+J32 -> -10 | K33: =IF(J33=0,0,L33/J33) -> 0 | L33: =IF(F33=0,L32-I33,L32+F33) -> 0
D34: 0 | E34: =IF(D34=0,0,F34/D34) -> 0 | F34: 0 | G34: 0 | H34: =K33 -> 0 | I34: =IF(F34=0,G34*H34,0) -> 0 | J34: =D34-G34+J33 -> -10 | K34: =IF(J34=0,0,L34/J34) -> 0 | L34: =IF(F34=0,L33-I34,L33+F34) -> 0
D35: 0 | E35: =IF(D35=0,0,F35/D35) -> 0 | F35: 0 | G35: 0 | H35: =K34 -> 0 | I35: =IF(F35=0,G35*H35,0) -> 0 | J35: =D35-G35+J34 -> -10 | K35: =IF(J35=0,0,L35/J35) -> 0 | L35: =IF(F35=0,L34-I35,L34+F35) -> 0
D36: 0 | E36: =IF(D36=0,0,F36/D36) -> 0 | F36: 0 | G36: 0 | H36: =K35 -> 0 | I36: =IF(F36=0,G36*H36,0) -> 0 | J36: =D36-G36+J35 -> -10 | K36: =IF(J36=0,0,L36/J36) -> 0 | L36: =IF(F36=0,L35-I36,L35+F36) -> 0
D37: 0 | E37: =IF(D37=0,0,F37/D37) -> 0 | F37: 0 | G37: 0 | H37: =K36 -> 0 | I37: =IF(F37=0,G37*H37,0) -> 0 | J37: =D37-G37+J36 -> -10 | K37: =IF(J37=0,0,L37/J37) -> 0 | L37: =IF(F37=0,L36-I37,L36+F37) -> 0
D38: 0 | E38: =IF(D38=0,0,F38/D38) -> 0 | F38: 0 | G38: 0 | H38: =K37 -> 0 | I38: =IF(F38=0,G38*H38,0) -> 0 | J38: =D38-G38+J37 -> -10 | K38: =IF(J38=0,0,L38/J38) -> 0 | L38: =IF(F38=0,L37-I38,L37+F38) -> 0
D39: 0 | E39: =IF(D39=0,0,F39/D39) -> 0 | F39: 0 | G39: 0 | H39: =K38 -> 0 | I39: =IF(F39=0,G39*H39,0) -> 0 | J39: =D39-G39+J38 -> -10 | K39: =IF(J39=0,0,L39/J39) -> 0 | L39: =IF(F39=0,L38-I39,L38+F39) -> 0
D40: 0 | E40: =IF(D40=0,0,F40/D40) -> 0 | F40: 0 | G40: 0 | H40: =K39 -> 0 | I40: =IF(F40=0,G40*H40,0) -> 0 | J40: =D40-G40+J39 -> -10 | K40: =IF(J40=0,0,L40/J40) -> 0 | L40: =IF(F40=0,L39-I40,L39+F40) -> 0
F41: 本期采购入库 | G41: =SUM(F27:F40) -> 0 | H41: 本期出库金额： | I41: =SUM(I27:I40) -> 0 | K41: 剩余总额 | L41: =L40 -> 0
A44: 库存商品成本期末移动平均结转报告
A45: 编制单位：XXX公司 | I45: 报告日期：2026/2/1
A46: 库存货品名称及批次 | B46: 期初数 | D46: 采购入库 | G46: 耗用出库 | J46: 结存
B47: 数量 | C47: 总计金额 | D47: 数量 | E47: 单价 | F47: 采购金额 | G47: 数量 | H47: 加权平均单价 | I47: 出库金额 | J47: 剩余数量 | K47: 加权平均单价 | L47: 剩余总额
A48: qwe | C48: =20*B48 -> 0 | L48: 0
D49: 0 | E49: =IF(D49=0,0,F49/D49) -> 0 | F49: 0 | G49: 0 | I49: =IF(F49=0,G49*H49,0) -> 0 | J49: =D49-G49+J48 -> 0 | K49: =IF(J49=0,0,L49/J49) -> 0 | L49: =IF(F49=0,L48-I49,L48+F49) -> 0
D50: 0 | E50: =IF(D50=0,0,F50/D50) -> 0 | F50: 0 | G50: 0 | H50: =K49 -> 0 | I50: =IF(F50=0,G50*H50,0) -> 0 | J50: =D50-G50+J49 -> 0 | K50: =IF(J50=0,0,L50/J50) -> 0 | L50: =IF(F50=0,L49-I50,L49+F50) -> 0
D51: 0 | E51: =IF(D51=0,0,F51/D51) -> 0 | F51: 0 | G51: 0 | H51: =K50 -> 0 | I51: =IF(F51=0,G51*H51,0) -> 0 | J51: =D51-G51+J50 -> 0 | K51: =IF(J51=0,0,L51/J51) -> 0 | L51: =IF(F51=0,L50-I51,L50+F51) -> 0
D52: 0 | E52: =IF(D52=0,0,F52/D52) -> 0 | F52: 0 | G52: 0 | H52: =K51 -> 0 | I52: =IF(F52=0,G52*H52,0) -> 0 | J52: =D52-G52+J51 -> 0 | K52: =IF(J52=0,0,L52/J52) -> 0 | L52: =IF(F52=0,L51-I52,L51+F52) -> 0
D53: 0 | E53: =IF(D53=0,0,F53/D53) -> 0 | F53: 0 | G53: 0 | H53: =K52 -> 0 | I53: =IF(F53=0,G53*H53,0) -> 0 | J53: =D53-G53+J52 -> 0 | K53: =IF(J53=0,0,L53/J53) -> 0 | L53: =IF(F53=0,L52-I53,L52+F53) -> 0
D54: 0 | E54: =IF(D54=0,0,F54/D54) -> 0 | F54: 0 | G54: 0 | H54: =K53 -> 0 | I54: =IF(F54=0,G54*H54,0) -> 0 | J54: =D54-G54+J53 -> 0 | K54: =IF(J54=0,0,L54/J54) -> 0 | L54: =IF(F54=0,L53-I54,L53+F54) -> 0
D55: 0 | E55: =IF(D55=0,0,F55/D55) -> 0 | F55: 0 | G55: 0 | H55: =K54 -> 0 | I55: =IF(F55=0,G55*H55,0) -> 0 | J55: =D55-G55+J54 -> 0 | K55: =IF(J55=0,0,L55/J55) -> 0 | L55: =IF(F55=0,L54-I55,L54+F55) -> 0
D56: 0 | E56: =IF(D56=0,0,F56/D56) -> 0 | F56: 0 | G56: 0 | H56: =K55 -> 0 | I56: =IF(F56=0,G56*H56,0) -> 0 | J56: =D56-G56+J55 -> 0 | K56: =IF(J56=0,0,L56/J56) -> 0 | L56: =IF(F56=0,L55-I56,L55+F56) -> 0
D57: 0 | E57: =IF(D57=0,0,F57/D57) -> 0 | F57: 0 | G57: 0 | H57: =K56 -> 0 | I57: =IF(F57=0,G57*H57,0) -> 0 | J57: =D57-G57+J56 -> 0 | K57: =IF(J57=0,0,L57/J57) -> 0 | L57: =IF(F57=0,L56-I57,L56+F57) -> 0
D58: 0 | E58: =IF(D58=0,0,F58/D58) -> 0 | F58: 0 | G58: 0 | H58: =K57 -> 0 | I58: =IF(F58=0,G58*H58,0) -> 0 | J58: =D58-G58+J57 -> 0 | K58: =IF(J58=0,0,L58/J58) -> 0 | L58: =IF(F58=0,L57-I58,L57+F58) -> 0
D59: 0 | E59: =IF(D59=0,0,F59/D59) -> 0 | F59: 0 | G59: 0 | H59: =K58 -> 0 | I59: =IF(F59=0,G59*H59,0) -> 0 | J59: =D59-G59+J58 -> 0 | K59: =IF(J59=0,0,L59/J59) -> 0 | L59: =IF(F59=0,L58-I59,L58+F59) -> 0
D60: 0 | E60: =IF(D60=0,0,F60/D60) -> 0 | F60: 0 | G60: 0 | H60: =K59 -> 0 | I60: =IF(F60=0,G60*H60,0) -> 0 | J60: =D60-G60+J59 -> 0 | K60: =IF(J60=0,0,L60/J60) -> 0 | L60: =IF(F60=0,L59-I60,L59+F60) -> 0
F61: 本期采购入库 | G61: =SUM(F49:F60) -> 0 | H61: 本期出库金额： | I61: =SUM(I49:I60) -> 0 | K61: 剩余总额 | L61: =L60 -> 0
A64: 库存商品成本期末移动平均结转报告
A65: 编制单位：XXX公司 | I65: 报告日期：2026/2/1
A66: 库存货品名称及批次 | B66: 期初数 | D66: 采购入库 | G66: 耗用出库 | J66: 结存
B67: 数量 | C67: 总计金额 | D67: 数量 | E67: 单价 | F67: 采购金额 | G67: 数量 | H67: 加权平均单价 | I67: 出库金额 | J67: 剩余数量 | K67: 加权平均单价 | L67: 剩余总额
A68: wer | C68: =20*B68 -> 0 | L68: 0
D69: 0 | E69: =IF(D69=0,0,F69/D69) -> 0 | F69: 0 | G69: 0 | I69: =IF(F69=0,G69*H69,0) -> 0 | J69: =D69-G69+J68 -> 0 | K69: =IF(J69=0,0,L69/J69) -> 0 | L69: =IF(F69=0,L68-I69,L68+F69) -> 0
D70: 0 | E70: =IF(D70=0,0,F70/D70) -> 0 | F70: 0 | G70: 0 | H70: =K69 -> 0 | I70: =IF(F70=0,G70*H70,0) -> 0 | J70: =D70-G70+J69 -> 0 | K70: =IF(J70=0,0,L70/J70) -> 0 | L70: =IF(F70=0,L69-I70,L69+F70) -> 0
D71: 0 | E71: =IF(D71=0,0,F71/D71) -> 0 | F71: 0 | G71: 0 | H71: =K70 -> 0 | I71: =IF(F71=0,G71*H71,0) -> 0 | J71: =D71-G71+J70 -> 0 | K71: =IF(J71=0,0,L71/J71) -> 0 | L71: =IF(F71=0,L70-I71,L70+F71) -> 0
D72: 0 | E72: =IF(D72=0,0,F72/D72) -> 0 | F72: 0 | G72: 0 | H72: =K71 -> 0 | I72: =IF(F72=0,G72*H72,0) -> 0 | J72: =D72-G72+J71 -> 0 | K72: =IF(J72=0,0,L72/J72) -> 0 | L72: =IF(F72=0,L71-I72,L71+F72) -> 0
D73: 0 | E73: =IF(D73=0,0,F73/D73) -> 0 | F73: 0 | G73: 0 | H73: =K72 -> 0 | I73: =IF(F73=0,G73*H73,0) -> 0 | J73: =D73-G73+J72 -> 0 | K73: =IF(J73=0,0,L73/J73) -> 0 | L73: =IF(F73=0,L72-I73,L72+F73) -> 0
D74: 0 | E74: =IF(D74=0,0,F74/D74) -> 0 | F74: 0 | G74: 0 | H74: =K73 -> 0 | I74: =IF(F74=0,G74*H74,0) -> 0 | J74: =D74-G74+J73 -> 0 | K74: =IF(J74=0,0,L74/J74) -> 0 | L74: =IF(F74=0,L73-I74,L73+F74) -> 0
D75: 0 | E75: =IF(D75=0,0,F75/D75) -> 0 | F75: 0 | G75: 0 | H75: =K74 -> 0 | I75: =IF(F75=0,G75*H75,0) -> 0 | J75: =D75-G75+J74 -> 0 | K75: =IF(J75=0,0,L75/J75) -> 0 | L75: =IF(F75=0,L74-I75,L74+F75) -> 0
D76: 0 | E76: =IF(D76=0,0,F76/D76) -> 0 | F76: 0 | G76: 0 | H76: =K75 -> 0 | I76: =IF(F76=0,G76*H76,0) -> 0 | J76: =D76-G76+J75 -> 0 | K76: =IF(J76=0,0,L76/J76) -> 0 | L76: =IF(F76=0,L75-I76,L75+F76) -> 0
D77: 0 | E77: =IF(D77=0,0,F77/D77) -> 0 | F77: 0 | G77: 0 | H77: =K76 -> 0 | I77: =IF(F77=0,G77*H77,0) -> 0 | J77: =D77-G77+J76 -> 0 | K77: =IF(J77=0,0,L77/J77) -> 0 | L77: =IF(F77=0,L76-I77,L76+F77) -> 0
D78: 0 | E78: =IF(D78=0,0,F78/D78) -> 0 | F78: 0 | G78: 0 | H78: =K77 -> 0 | I78: =IF(F78=0,G78*H78,0) -> 0 | J78: =D78-G78+J77 -> 0 | K78: =IF(J78=0,0,L78/J78) -> 0 | L78: =IF(F78=0,L77-I78,L77+F78) -> 0
D79: 0 | E79: =IF(D79=0,0,F79/D79) -> 0 | F79: 0 | G79: 0 | H79: =K78 -> 0 | I79: =IF(F79=0,G79*H79,0) -> 0 | J79: =D79-G79+J78 -> 0 | K79: =IF(J79=0,0,L79/J79) -> 0 | L79: =IF(F79=0,L78-I79,L78+F79) -> 0
D80: 0 | E80: =IF(D80=0,0,F80/D80) -> 0 | F80: 0 | G80: 0 | H80: =K79 -> 0 | I80: =IF(F80=0,G80*H80,0) -> 0 | J80: =D80-G80+J79 -> 0 | K80: =IF(J80=0,0,L80/J80) -> 0 | L80: =IF(F80=0,L79-I80,L79+F80) -> 0
F81: 本期采购入库 | G81: =SUM(F69:F80) -> 0 | H81: 本期出库金额： | I81: =SUM(I69:I80) -> 0 | K81: 剩余总额 | L81: =L80 -> 0
A84: 库存商品成本期末移动平均结转报告
A85: 编制单位：XXX公司 | I85: 报告日期：2026/2/1
A86: 库存货品名称及批次 | B86: 期初数 | D86: 采购入库 | G86: 耗用出库 | J86: 结存
B87: 数量 | C87: 总计金额 | D87: 数量 | E87: 单价 | F87: 采购金额 | G87: 数量 | H87: 加权平均单价 | I87: 出库金额 | J87: 剩余数量 | K87: 加权平均单价 | L87: 剩余总额
A88: rty | C88: =20*B88 -> 0 | L88: 0
D89: 0 | E89: =IF(D89=0,0,F89/D89) -> 0 | F89: 0 | G89: 0 | I89: =IF(F89=0,G89*H89,0) -> 0 | J89: =D89-G89+J88 -> 0 | K89: =IF(J89=0,0,L89/J89) -> 0 | L89: =IF(F89=0,L88-I89,L88+F89) -> 0
D90: 0 | E90: =IF(D90=0,0,F90/D90) -> 0 | F90: 0 | G90: 0 | H90: =K89 -> 0 | I90: =IF(F90=0,G90*H90,0) -> 0 | J90: =D90-G90+J89 -> 0 | K90: =IF(J90=0,0,L90/J90) -> 0 | L90: =IF(F90=0,L89-I90,L89+F90) -> 0
D91: 0 | E91: =IF(D91=0,0,F91/D91) -> 0 | F91: 0 | G91: 0 | H91: =K90 -> 0 | I91: =IF(F91=0,G91*H91,0) -> 0 | J91: =D91-G91+J90 -> 0 | K91: =IF(J91=0,0,L91/J91) -> 0 | L91: =IF(F91=0,L90-I91,L90+F91) -> 0
D92: 0 | E92: =IF(D92=0,0,F92/D92) -> 0 | F92: 0 | G92: 0 | H92: =K91 -> 0 | I92: =IF(F92=0,G92*H92,0) -> 0 | J92: =D92-G92+J91 -> 0 | K92: =IF(J92=0,0,L92/J92) -> 0 | L92: =IF(F92=0,L91-I92,L91+F92) -> 0
D93: 0 | E93: =IF(D93=0,0,F93/D93) -> 0 | F93: 0 | G93: 0 | H93: =K92 -> 0 | I93: =IF(F93=0,G93*H93,0) -> 0 | J93: =D93-G93+J92 -> 0 | K93: =IF(J93=0,0,L93/J93) -> 0 | L93: =IF(F93=0,L92-I93,L92+F93) -> 0
D94: 0 | E94: =IF(D94=0,0,F94/D94) -> 0 | F94: 0 | G94: 0 | H94: =K93 -> 0 | I94: =IF(F94=0,G94*H94,0) -> 0 | J94: =D94-G94+J93 -> 0 | K94: =IF(J94=0,0,L94/J94) -> 0 | L94: =IF(F94=0,L93-I94,L93+F94) -> 0
D95: 0 | E95: =IF(D95=0,0,F95/D95) -> 0 | F95: 0 | G95: 0 | H95: =K94 -> 0 | I95: =IF(F95=0,G95*H95,0) -> 0 | J95: =D95-G95+J94 -> 0 | K95: =IF(J95=0,0,L95/J95) -> 0 | L95: =IF(F95=0,L94-I95,L94+F95) -> 0
D96: 0 | E96: =IF(D96=0,0,F96/D96) -> 0 | F96: 0 | G96: 0 | H96: =K95 -> 0 | I96: =IF(F96=0,G96*H96,0) -> 0 | J96: =D96-G96+J95 -> 0 | K96: =IF(J96=0,0,L96/J96) -> 0 | L96: =IF(F96=0,L95-I96,L95+F96) -> 0
D97: 0 | E97: =IF(D97=0,0,F97/D97) -> 0 | F97: 0 | G97: 0 | H97: =K96 -> 0 | I97: =IF(F97=0,G97*H97,0) -> 0 | J97: =D97-G97+J96 -> 0 | K97: =IF(J97=0,0,L97/J97) -> 0 | L97: =IF(F97=0,L96-I97,L96+F97) -> 0
D98: 0 | E98: =IF(D98=0,0,F98/D98) -> 0 | F98: 0 | G98: 0 | H98: =K97 -> 0 | I98: =IF(F98=0,G98*H98,0) -> 0 | J98: =D98-G98+J97 -> 0 | K98: =IF(J98=0,0,L98/J98) -> 0 | L98: =IF(F98=0,L97-I98,L97+F98) -> 0
D99: 0 | E99: =IF(D99=0,0,F99/D99) -> 0 | F99: 0 | G99: 0 | H99: =K98 -> 0 | I99: =IF(F99=0,G99*H99,0) -> 0 | J99: =D99-G99+J98 -> 0 | K99: =IF(J99=0,0,L99/J99) -> 0 | L99: =IF(F99=0,L98-I99,L98+F99) -> 0
D100: 0 | E100: =IF(D100=0,0,F100/D100) -> 0 | F100: 0 | G100: 0 | H100: =K99 -> 0 | I100: =IF(F100=0,G100*H100,0) -> 0 | J100: =D100-G100+J99 -> 0 | K100: =IF(J100=0,0,L100/J100) -> 0 | L100: =IF(F100=0,L99-I100,L99+F100) -> 0
F101: 本期采购入库 | G101: =SUM(F89:F100) -> 0 | H101: 本期出库金额： | I101: =SUM(I89:I100) -> 0 | K101: 剩余总额 | L101: =L100 -> 0
A104: 库存商品成本期末移动平均结转报告
A105: 编制单位：XXX公司 | I105: 报告日期：2026/2/1
A106: 库存货品名称及批次 | B106: 期初数 | D106: 采购入库 | G106: 耗用出库 | J106: 结存
B107: 数量 | C107: 总计金额 | D107: 数量 | E107: 单价 | F107: 采购金额 | G107: 数量 | H107: 加权平均单价 | I107: 出库金额 | J107: 剩余数量 | K107: 加权平均单价 | L107: 剩余总额
A108: tyui | C108: =20*B108 -> 0 | L108: 0
D109: 0 | E109: =IF(D109=0,0,F109/D109) -> 0 | F109: 0 | G109: 0 | I109: =IF(F109=0,G109*H109,0) -> 0 | J109: =D109-G109+J108 -> 0 | K109: =IF(J109=0,0,L109/J109) -> 0 | L109: =IF(F109=0,L108-I109,L108+F109) -> 0
...

Sheet 明细账汇总-资产类科目
B1: 银行存款 | F1: 土地使用权 | J1: 原材料 | N1: 半成品（零件） | Q1: 固定资产 | Y1: 应收账款 | AD1: 应付账款 | AH1: 库存商品 | AL1: 工业产权及专有技术 | AP1: 累计折旧 | AT1: 交易性金融资产
B2: 借方（增加） | C2: 贷方（减少） | F2: 借方（增加） | G2: 贷方（减少） | J2: 借方（增加） | K2: 贷方（减少） | N2: 借方（增加） | O2: 贷方（减少） | Q2: 借方（增加） | R2: 贷方（减少） | Y2: 借方（增加） | Z2: 贷方（减少） | AD2: 借方（增加） | AE2: 贷方（减少） | AH2: 借方（增加） | AI2: 贷方（减少） | AL2: 借方（增加） | AM2: 贷方（减少） | AP2: 借方（减少） | AQ2: 贷方（增加） | AT2: 借方（增加） | AU2: 贷方（减少）
A3: 期初 | E3: 期初 | I3: 期初 | M3: 期初 | P3: 期初 | X3: 期初 | AC3: 期初 | AG3: 期初 | AK3: 期初 | AL3: 0 | AO3: 期初 | AP3: 0 | AS3: 期初
G4: 0 | J4: ='原材料(加工用)'!L204 -> 0 | N4: ='零件（加工用）'!L203 -> 411.2 | R4: 0 | Z4: 0 | AD4: 0 | AE4: 0 | AH4: ='商品（各实体用）'!L185 -> 20.56 | AI4: 0 | AM4: 0 | AQ4: 0
A26: 本期累计发生 | B26: =SUM(B4:B25) -> 0 | C26: =SUM(C4:C25) -> 0 | E26: 本期累计发生 | F26: =SUM(F4:F25) -> 0 | G26: =SUM(G4:G25) -> 0 | I26: 本期累计发生 | J26: =SUM(J4:J25) -> 0 | K26: =SUM(K4:K25) -> 0 | M26: 本期累计发生 | N26: =SUM(N4:N25) -> 411.2 | O26: =SUM(O4:O25) -> 0 | P26: 本期累计发生 | Q26: =SUM(Q4:Q25) -> 0 | R26: =SUM(R4:R25) -> 0 | X26: 本期累计发生 | Y26: =SUM(Y4:Y25) -> 0 | Z26: =SUM(Z4:Z25) -> 0 | AC26: 本期累计发生 | AD26: =SUM(AD4:AD25) -> 0 | AE26: =SUM(AE4:AE25) -> 0 | AG26: 本期累计发生 | AH26: =SUM(AH4:AH25) -> 20.56 | AI26: =SUM(AI4:AI25) -> 0 | AK26: 本期累计发生 | AL26: =SUM(AL4:AL25) -> 0 | AM26: =SUM(AM4:AM25) -> 0 | AO26: 本期累计发生 | AP26: =SUM(AP4:AP25) -> 0 | AQ26: =SUM(AQ4:AQ25) -> 0 | AS26: 本期累计发生 | AT26: =SUM(AT4:AT25) -> 0 | AU26: =SUM(AU4:AU25) -> 0
A27: 本期余额 | B27: =B26-C26 -> 0 | C27: =B27-银行流水账!F162 -> 0 | E27: 本期余额 | F27: =F3+F26-G26 -> 0 | I27: 本期余额 | J27: =J3+J26-K26 -> 0 | M27: 本期余额 | N27: =N3+N26-O26 -> 411.2 | P27: 本期余额 | Q27: =Q3+Q26-R26 -> 0 | X27: 本期余额 | Y27: =Y3+Y26-Z26 -> 0 | AC27: 本期余额 | AD27: =AD3+AD26-AE26 -> 0 | AG27: 本期余额 | AH27: =AH3+AH26-AI26 -> 20.56 | AK27: 本期余额 | AL27: =AL3+AL26-AM26 -> 0 | AO27: 本期余额 | AP27: =AQ26-AP26 -> 0 | AS27: 本期余额 | AT27: =AT26-AU26 -> 0

Sheet 明细账汇总-负债类科目
B1: 预收账款 | F1: 短期借款 | K1: 应付账款 | P1: 应付职工薪酬
B2: 借方（减少） | C2: 贷方(增加） | F2: 借方（减少） | G2: 贷方（增加） | K2: 借方（减少） | L2: 贷方（增加） | P2: 借方（减少） | Q2: 贷方（增加）
A3: 期初 | E3: 期初 | J3: 期初 | O3: 期初
C4: 0 | G4: 0 | L4: 0 | Q4: 0
A20: 本期累计发生 | B20: =SUM(B4:B19) -> 0 | C20: =SUM(C4:C19) -> 0 | E20: 本期累计发生 | F20: =SUM(F4:F19) -> 0 | G20: =SUM(G4:G19) -> 0 | J20: 本期累计发生 | K20: =SUM(K4:K19) -> 0 | L20: =SUM(L4:L19) -> 0 | O20: 本期累计发生 | P20: =SUM(P4:P19) -> 0 | Q20: =SUM(Q4:Q19) -> 0
A21: 本期余额 | B21: =C3+C20-B20 -> 0 | E21: 本期余额 | F21: =G3+G20-F20 -> 0 | J21: 本期余额 | K21: =L3+L20-K20 -> 0 | O21: 本期余额 | P21: =Q3+Q20-P20 -> 0

Sheet 明细账汇总-损益类科目
B1: 产品（商品）销售收入 | F1: 投资收益 | J1: 其他业务收入 | N1: 主营业务成本-存货成本 | R1: 主营业务成本-人工 | V1: 主营业务税金及附加 | Z1: 销售费用 | AD1: 管理费用 | AH1: 财务费用（利息费用） | AL1: 实收资本 | AP1: 资本公积 | AT1: 未分配利润 | AX1: 营业外收入
B2: 借方（减少） | C2: 贷方(增加） | F2: 借方（减少） | G2: 贷方(增加） | J2: 借方（减少） | K2: 贷方(增加） | N2: 借方（增加） | O2: 贷方(减少） | R2: 借方（增加） | S2: 贷方(减少） | V2: 借方（增加） | W2: 贷方（减少） | Z2: 借方（增加） | AA2: 贷方（减少） | AD2: 借方（增加） | AE2: 贷方（减少） | AH2: 借方（增加） | AI2: 贷方（减少） | AL2: 借方（减少） | AM2: 贷方(增加） | AP2: 借方（减少） | AQ2: 贷方(增加） | AT2: 借方（减少） | AU2: 贷方(增加） | AX2: 借方（减少） | AY2: 贷方(增加）
C3: 0 | G3: 0 | K3: 0 | N3: ='商品（各实体用）'!L186 -> 0 | O3: 0 | S3: 0 | W3: 0 | AA3: 0 | AE3: 0 | AI3: 0 | AM3: 0 | AQ3: 0 | AU3: 0 | AY3: 0
A24: 本期累计发生 | B24: =SUM(B3:B23) -> 0 | C24: =SUM(C3:C23) -> 0 | E24: 本期累计发生 | F24: =SUM(F3:F23) -> 0 | G24: =SUM(G3:G23) -> 0 | I24: 本期累计发生 | J24: =SUM(J3:J23) -> 0 | K24: =SUM(K3:K23) -> 0 | M24: 本期累计发生 | N24: =SUM(N3:N23) -> 0 | O24: =SUM(O3:O23) -> 0 | Q24: 本期累计发生 | R24: =SUM(R3:R23) -> 0 | S24: =SUM(S3:S23) -> 0 | U24: 本期累计发生 | V24: =SUM(V3:V23) -> 0 | W24: =SUM(W3:W23) -> 0 | Y24: 本期累计发生 | Z24: =SUM(Z3:Z23) -> 0 | AA24: =SUM(AA3:AA23) -> 0 | AC24: 本期累计发生 | AD24: =SUM(AD3:AD23) -> 0 | AE24: =SUM(AE3:AE23) -> 0 | AG24: 本期累计发生 | AH24: =SUM(AH3:AH23) -> 0 | AI24: =SUM(AI3:AI23) -> 0 | AK24: 本期累计发生 | AL24: =SUM(AL3:AL23) -> 0 | AM24: =SUM(AM3:AM23) -> 0 | AO24: 本期累计发生 | AP24: =SUM(AP3:AP23) -> 0 | AQ24: =SUM(AQ3:AQ23) -> 0 | AS24: 本期累计发生 | AT24: =SUM(AT3:AT23) -> 0 | AU24: =SUM(AU3:AU23) -> 0 | AW24: 本期累计发生 | AX24: =SUM(AX3:AX23) -> 0 | AY24: =SUM(AY3:AY23) -> 0
A25: 本期余额 | B25: =C24-B24 -> 0 | E25: 本期余额 | F25: =G24-F24 -> 0 | I25: 本期余额 | J25: =K24-J24 -> 0 | M25: 本期余额 | N25: =N24-O24 -> 0 | Q25: 本期余额 | R25: =R24-S24 -> 0 | U25: 本期余额 | V25: =V24-W24 -> 0 | Y25: 本期余额 | Z25: =Z24-AA24 -> 0 | AC25: 本期余额 | AD25: =AD24-AE24 -> 0 | AG25: 本期余额 | AH25: =AH24-AI24 -> 0 | AK25: 本期余额 | AL25: =AM24-AL24 -> 0 | AO25: 本期余额 | AP25: =AQ24-AP24 -> 0 | AS25: 本期余额 | AT25: =AU24-AT24 -> 0 | AW25: 本期余额 | AX25: =AY24-AX24 -> 0

Sheet 资产负债表
D2: 资产负债表
A4: XX贸易有限公司 | D4: 2026年 7月 1日
A6: 资 产 | B6: 行次 | C6: 期初数 | D6: 期末数 | E6: 负债及所有者权益 | F6: 行次 | G6: 期初数 | H6: 期末数
A7: 流动资产： | B7: 1 | E7: 流动负债： | F7: 74
A8: 现金 | B8: 2 | C8: 0 | D8: 0 | E8: 短期借款 | F8: 75 | G8: 0 | H8: ='明细账汇总-负债类科目'!F21 -> 0
A9: 银行存款 | B9: 3 | D9: ='明细账汇总-资产类科目'!B27 -> 0 | E9: 应付票据 | F9: 76 | G9: 0 | H9: 0
A10: 交易性金融资产 | B10: 4 | D10: ='明细账汇总-资产类科目'!AT27 -> 0 | E10: 应付帐款 | F10: 77 | G10: 0 | H10: ='明细账汇总-负债类科目'!K21 -> 0
A11: 应收票据 | B11: 5 | E11: 预收帐款 | F11: 78 | G11: 0 | H11: ='明细账汇总-负债类科目'!B21 -> 0
A12: 应收股利 | B12: 6 | E12: 应付工资 | F12: 79 | G12: ='明细账汇总-负债类科目'!Q3 -> 0 | H12: ='明细账汇总-负债类科目'!P21 -> 0
A13: 应收利息 | B13: 7 | E13: 应付福利费 | F13: 80 | G13: 0 | H13: 0
A14: 应收帐款 | B14: 8 | C14: 0 | D14: ='明细账汇总-资产类科目'!Y27 -> 0 | E14: 应付股利 | F14: 81 | G14: 0 | H14: 0
A15: 减：坏帐准备 | B15: 9 | E15: 应交税金 | F15: 82 | G15: 0 | H15: 0
A16: 其他应收款 | B16: 10 | C16: 0 | D16: 0 | E16: 其他应交款 | F16: 83 | G16: 0 | H16: 0
A17: 预付帐款 | B17: 11 | C17: 0 | D17: 0 | E17: 其他应付款 | F17: 84 | G17: 0 | H17: 0
A18: 应收补贴款 | B18: 12 | E18: 预提费用 | F18: 85 | G18: 0
A19: 原材料 | B19: 13 | D19: ='明细账汇总-资产类科目'!J27+'明细账汇总-资产类科目'!N27 -> 411.2 | E19: 预计负债 | F19: 86 | G19: 0
A20: 减：存货变现损失准备 | B20: 14 | F20: 87 | G20: 0
A21: 库存商品 | B21: 15 | D21: ='明细账汇总-资产类科目'!AH27 -> 20.56 | F21: 88 | G21: 0
B22: 16 | F22: 89
B23: 17 | F23: 90
B24: 18 | F24: 91
B25: 19 | F25: 92
A26: 1年内到期的长期债权投资 | B26: 20 | E26: 1年内到期的长期负债 | F26: 93 | G26: 0
A27: 其他流动资产 | B27: 21 | E27: 其他流动负债 | F27: 94 | G27: 0
A28: 流动资产合计 | B28: 22 | C28: =SUM(C8:C14)-C15+C16+C17+C18+C19-C20+C21+C26+C27 -> 0 | D28: =SUM(D8:D19)-D20+D21+D26+D27 -> 431.76 | E28: 流动负债合计 | F28: 95 | G28: =SUM(G8:G27) -> 0 | H28: =SUM(H8:H27) -> 0
A29: 长期投资： | B29: 23 | E29: 长期负债： | F29: 96
A30: 长期股权投资 | B30: 24 | C30: 0 | D30: 0 | E30: 长期借款 | F30: 97 | G30: 0 | H30: 0
A31: 长期债权投资 | B31: 25 | C31: 0 | D31: 0 | E31: 应付债券 | F31: 98 | G31: 0 | H31: 0
B32: 26 | E32: 长期应付款 | F32: 99 | G32: 0 | H32: 0
B33: 27 | E33: 专项应付款 | F33: 100 | G33: 0 | H33: 0
B34: 28 | E34: 其他长期负债 | F34: 101 | G34: 0 | H34: 0
B35: 29 | F35: 102
B36: 30 | F36: 103
B37: 31 | F37: 104
B38: 32 | F38: 105
B39: 33 | F39: 106
B40: 34 | F40: 107
B41: 35 | F41: 108
B42: 36 | F42: 109
B43: 37 | F43: 110
A44: 长期投资合计 | B44: 38 | C44: =C30+C31 -> 0 | D44: =D30+D31 -> 0 | E44: 长期负债合计 | F44: 111 | G44: =SUM(G30:G34) -> 0 | H44: =SUM(H30:H34) -> 0
A45: 固定资产： | B45: 39 | E45: 其他负债： | F45: 112
A46: 固定资产原价 | B46: 40 | C46: 0 | D46: ='明细账汇总-资产类科目'!Q27 -> 0 | E46: 递延税款贷项 | F46: 113 | G46: 0 | H46: 0
A47: 累计折旧 | B47: 41 | C47: 0 | D47: ='明细账汇总-资产类科目'!AP27 -> 0 | E47: 递延投资收益 | F47: 114 | G47: 0 | H47: 0
A48: 固定资产净值 | B48: 42 | C48: =C46-C47 -> 0 | D48: =D46-D47 -> 0 | E48: 其他递延贷项 | F48: 115 | G48: 0 | H48: 0
A49: 固定资产减值准备 | B49: 43 | F49: 116
A50: 固定资产净额 | B50: 44 | F50: 117
A51: 工程物资 | B51: 45 | F51: 118
A52: 在建工程 | B52: 46 | F52: 119
A53: 固定资产清理 | B53: 47 | F53: 120
B54: 48 | F54: 121
A55: 固定资产合计 | B55: 49 | C55: =SUM(C48:C54) -> 0 | D55: =SUM(D48:D54) -> 0 | E55: 其他负债合计 | F55: 122 | G55: =SUM(G46:G48) -> 0 | H55: =SUM(H46:H48) -> 0
B56: 50 | E56: 负债合计 | F56: 123 | G56: =G28+G44+G55 -> 0 | H56: =H28+H44+H55 -> 0
B57: 51 | E57: 所有者权益： | F57: 124
B58: 52 | E58: 资本总额 | F58: 125
B59: 53 | E59: (货币名称及金额 ) | F59: 126
A60: 无形资产： | B60: 54 | E60: 实收资本 | F60: 127 | H60: ='明细账汇总-损益类科目'!AL25 -> 0
A61: 土地使用权 | B61: 55 | C61: 0 | D61: ='明细账汇总-资产类科目'!F27 -> 0 | E61: (非人民币资本期末余额 )
A62: 工业产权及专有技术 | B62: 56 | C62: 0 | D62: ='明细账汇总-资产类科目'!AL27 -> 0 | E62: 其中：中方投资 | F62: 129
A63: 其他无形资产 | B63: 57 | C63: 0 | D63: 0 | E63: (非人民币资本期末余额 ) | F63: 130
B64: 58 | E64: 外方投资 | F64: 131
B65: 59 | E65: (非人民币资本期末余额 ) | F65: 132
B66: 60 | E66: 减：已归还投资 | F66: 133
A67: 无形资产合计 | B67: 61 | C67: =SUM(C57:C63) -> 0 | D67: =SUM(D57:D63) -> 0 | E67: 资本公积 | F67: 134 | H67: ='明细账汇总-损益类科目'!AP25 -> 0
A68: 其他资产： | B68: 62 | E68: 盈余公积 | F68: 135 | G68: 0 | H68: 0
A69: 开办费 | B69: 63 | E69: 其中：法定公益金 | F69: 136
A70: 其他长期资产 | B70: 64 | F70: 137
B71: 65 | E71: 本年利润 | F71: 138 | G71: 0 | H71: =利润表!C37 -> 0
A72: 递延税款借项 | B72: 66 | E72: 未分配利润 | F72: 139 | G72: 0 | H72: ='明细账汇总-损益类科目'!AT25 -> 0
B73: 67 | F73: 140
B74: 68 | F74: 141
B75: 69 | F75: 142
B76: 70 | F76: 143
B77: 71 | F77: 144
A78: 其他资产合计 | B78: 72 | C78: =SUM(C69:C73) -> 0 | D78: 0 | E78: 所有者权益合计 | F78: 145 | G78: =SUM(G58+G60-G66+G67+G68+G71+G72) -> 0 | H78: =SUM(H58+H60-H66+H67+H68+H71+H72) -> 0
A79: 资产总计 | B79: 73 | C79: =C78+C55+C28+C67 -> 0 | D79: =D78+D55+D28+D67 -> 431.76 | E79: 负债及所有者权益总计 | F79: 146 | G79: =G78+G56 -> 0 | H79: =H78+H56 -> 0
G80: =C79-G79 -> 0 | H80: =D79-H79 -> 431.76

Sheet 利润表
B1: 利润表
B2: 2026年 7月 1日
A5: =资产负债表!A4 -> XX贸易有限公司
A6: 项 目 | B6: 行次 | C6: 本年累计数
A7: 主营业务收入 | B7: 1 | C7: =C8+C9 -> 0
A8: 其中：产品（商品）销售收入 | B8: 2 | C8: ='明细账汇总-损益类科目'!B25 -> 0
B9: 3
B10: 4
B11: 5
A12: 主营业务收入 | B12: 6 | C12: =C7 -> 0
A13: 减：主营业务成本 | B13: 7 | C13: ='明细账汇总-损益类科目'!N25+'明细账汇总-损益类科目'!R25 -> 0
A14: 主营业务税金及附加 | B14: 8 | C14: ='明细账汇总-损益类科目'!V25 -> 0
B15: 9
B16: 10
B17: 11
A18: 主营业务利润 | B18: 12 | C18: =C12-C13-C14 -> 0
A19: 减：营业费用 | B19: 13 | C19: ='明细账汇总-损益类科目'!Z25 -> 0
A20: 管理费用 | B20: 14 | C20: ='明细账汇总-损益类科目'!AD25 -> 0
A21: 财务费用 | B21: 15 | C21: ='明细账汇总-损益类科目'!AH25 -> 0
A22: 其中：利息支出(减利息收入) | B22: 16 | C22: 0
A23: 汇兑损失(减汇兑收益) | B23: 17 | C23: 0
B24: 18
A25: 加：其他业务收入 | B25: 19 | C25: ='明细账汇总-损益类科目'!J25 -> 0
B26: 20
A27: 减：存货跌价损失 | B27: 21 | C27: 0
A28: 营业利润 | B28: 22 | C28: =C18-C19-C20-C21+C25 -> 0
A29: 加：投资收益 | B29: 23 | C29: ='明细账汇总-损益类科目'!F25 -> 0
A30: 补贴收入 | B30: 24
A31: 营业外收入 | B31: 25 | C31: ='明细账汇总-损益类科目'!AX25 -> 0
A32: 减：营业外支出 | B32: 26 | C32: 0
B33: 27
B34: 28
A35: 利润总额 | B35: 29 | C35: =C28+C29+C30+C31-C32 -> 0
A36: 减：所得税 | B36: 30 | C36: 0
A37: 净利润 | B37: 31 | C37: =C35-C36 -> 0

Sheet 计算
I1: 取得的销售货物收到的现金 | K1: 取得的提供服务到的现金 | M1: 收取利息、手续费及佣金的现金 | O1: 处置交易性金融资产净增加额 | Q1: 回购业务资金净增加额 | S1: 收到其他与经营活动有关的现金 | U1: 支付给职工以及为职工支付的现金 | W1: 支付的各项税费 | Y1: 回购业务资金净减少额 | AA1: 支付其他与经营活动有关的现金 | AC1: 收回投资收到的现金 | AE1: 取得投资收益收到的现金 | AG1: 处置固定资产、无形资产和其他长期资产收到的现金净额 | AI1: 收到其他与投资活动有关的现金 | AK1: 投资支付现金 | AM1: 购建固定资产、无形资产和其他长期资产支付的现金 | AO1: 吸收投资收到的现金 | AQ1: 取得借款收到的现金 | AS1: 收到其他与筹资活动有关的现金 | AU1: 偿还债务支付的现金 | AW1: 分配股利、利润或偿付利息支付的现金 | AY1: 支付其他与筹资活动有关的现金
A2: 存款增加 | B2: 存款减少 | C2: 现金流性质分析 | H2: 增加 | I2: 减少 | J2: 增加 | K2: 减少 | L2: 增加 | M2: 减少 | N2: 增加 | O2: 减少 | P2: 增加 | Q2: 减少 | R2: 增加 | S2: 减少 | T2: 增加 | U2: 减少 | V2: 增加 | W2: 减少 | X2: 增加 | Y2: 减少 | Z2: 增加 | AA2: 减少 | AB2: 增加 | AC2: 减少 | AD2: 增加 | AE2: 减少 | AF2: 增加 | AG2: 减少 | AH2: 增加 | AI2: 减少 | AJ2: 增加 | AK2: 减少 | AL2: 增加 | AM2: 减少 | AN2: 增加 | AO2: 减少 | AP2: 增加 | AQ2: 减少 | AR2: 增加 | AS2: 减少 | AT2: 增加 | AU2: 减少 | AV2: 增加 | AW2: 减少 | AX2: 增加 | AY2: 减少
H4: =IF(C4="取得的销售货物收到的现金",A4,"0") -> 0 | I4: =IF(C4="取得的销售货物收到的现金",B4,"0") -> 0 | J4: =IF(C4="取得的提供服务到的现金",A4,"0") -> 0 | K4: =IF(C4="取得的提供服务到的现金",B4,"0") -> 0 | L4: =IF(C4="收取利息、手续费及佣金的现金",A4,"0") -> 0 | M4: =IF(C4="收取利息、手续费及佣金的现金",B4,"0") -> 0 | N4: =IF(C4="处置交易性金融资产净增加额",A4,"0") -> 0 | O4: =IF(C4="处置交易性金融资产净增加额",B4,"0") -> 0 | P4: =IF(C4="回购业务资金净增加额",A4,"0") -> 0 | Q4: =IF(C4="回购业务资金净增加额",B4,"0") -> 0 | R4: =IF(C4="收到其他与经营活动有关的现金",A4,"0") -> 0 | S4: =IF(C4="收到其他与经营活动有关的现金",B4,"0") -> 0 | T4: =IF(C4="支付给职工以及为职工支付的现金",A4,"0") -> 0 | U4: =IF(C4="支付给职工以及为职工支付的现金",B4,"0") -> 0 | V4: =IF(C4="支付的各项税费",A4,"0") -> 0 | W4: =IF(C4="支付的各项税费",B4,"0") -> 0 | X4: =IF(C4="回购业务资金净减少额",A4,"0") -> 0 | Y4: =IF(C4="回购业务资金净减少额",B4,"0") -> 0 | Z4: =IF(C4="支付其他与经营活动有关的现金",A4,"0") -> 0 | AA4: =IF(C4="支付其他与经营活动有关的现金",B4,"0") -> 0 | AB4: =IF(C4="收回投资收到的现金",A4,"0") -> 0 | AC4: =IF(C4="收回投资收到的现金",B4,"0") -> 0 | AD4: =IF(C4="取得投资收益收到的现金",A4,"0") -> 0 | AE4: =IF(C4="取得投资收益收到的现金",B4,"0") -> 0 | AF4: =IF(C4="处置固定资产、无形资产和其他长期资产收到的现金净额",A4,"0") -> 0 | AG4: =IF(C4="处置固定资产、无形资产和其他长期资产收到的现金净额",B4,"0") -> 0 | AH4: =IF(C4="收到其他与投资活动有关的现金",A4,"0") -> 0 | AI4: =IF(C4="收到其他与投资活动有关的现金",B4,"0") -> 0 | AJ4: =IF(C4="投资支付现金",A4,"0") -> 0 | AK4: =IF(C4="投资支付现金",B4,"0") -> 0 | AL4: =IF(C4="购建固定资产、无形资产和其他长期资产支付的现金",A4,"0") -> 0 | AM4: =IF(C4="购建固定资产、无形资产和其他长期资产支付的现金",B4,"0") -> 0 | AN4: =IF(C4="吸收投资收到的现金",A4,"0") -> 0 | AO4: =IF(C4="吸收投资收到的现金",B4,"0") -> 0 | AP4: =IF(C4="取得借款收到的现金",A4,"0") -> 0 | AQ4: =IF(C4="取得借款收到的现金",B4,"0") -> 0 | AR4: =IF(C4="收到其他与筹资活动有关的现金",A4,"0") -> 0 | AS4: =IF(C4="收到其他与筹资活动有关的现金",B4,"0") -> 0 | AT4: =IF(C4="偿还债务支付的现金",A4,"0") -> 0 | AU4: =IF(C4="偿还债务支付的现金",B4,"0") -> 0 | AV4: =IF(C4="分配股利、利润或偿付利息支付的现金",A4,"0") -> 0 | AW4: =IF(C4="分配股利、利润或偿付利息支付的现金",B4,"0") -> 0 | AX4: =IF(C4="支付其他与筹资活动有关的现金",A4,"0") -> 0 | AY4: =IF(C4="支付其他与筹资活动有关的现金",B4,"0") -> 0
H5: =IF(C5="取得的销售货物收到的现金",A5,"0") -> 0 | I5: =IF(C5="取得的销售货物收到的现金",B5,"0") -> 0 | J5: =IF(C5="取得的提供服务到的现金",A5,"0") -> 0 | K5: =IF(C5="取得的提供服务到的现金",B5,"0") -> 0 | L5: =IF(C5="收取利息、手续费及佣金的现金",A5,"0") -> 0 | M5: =IF(C5="收取利息、手续费及佣金的现金",B5,"0") -> 0 | N5: =IF(C5="处置交易性金融资产净增加额",A5,"0") -> 0 | O5: =IF(C5="处置交易性金融资产净增加额",B5,"0") -> 0 | P5: =IF(C5="回购业务资金净增加额",A5,"0") -> 0 | Q5: =IF(C5="回购业务资金净增加额",B5,"0") -> 0 | R5: =IF(C5="收到其他与经营活动有关的现金",A5,"0") -> 0 | S5: =IF(C5="收到其他与经营活动有关的现金",B5,"0") -> 0 | T5: =IF(C5="支付给职工以及为职工支付的现金",A5,"0") -> 0 | U5: =IF(C5="支付给职工以及为职工支付的现金",B5,"0") -> 0 | V5: =IF(C5="支付的各项税费",A5,"0") -> 0 | W5: =IF(C5="支付的各项税费",B5,"0") -> 0 | X5: =IF(C5="回购业务资金净减少额",A5,"0") -> 0 | Y5: =IF(C5="回购业务资金净减少额",B5,"0") -> 0 | Z5: =IF(C5="支付其他与经营活动有关的现金",A5,"0") -> 0 | AA5: =IF(C5="支付其他与经营活动有关的现金",B5,"0") -> 0 | AB5: =IF(C5="收回投资收到的现金",A5,"0") -> 0 | AC5: =IF(C5="收回投资收到的现金",B5,"0") -> 0 | AD5: =IF(C5="取得投资收益收到的现金",A5,"0") -> 0 | AE5: =IF(C5="取得投资收益收到的现金",B5,"0") -> 0 | AF5: =IF(C5="处置固定资产、无形资产和其他长期资产收到的现金净额",A5,"0") -> 0 | AG5: =IF(C5="处置固定资产、无形资产和其他长期资产收到的现金净额",B5,"0") -> 0 | AH5: =IF(C5="收到其他与投资活动有关的现金",A5,"0") -> 0 | AI5: =IF(C5="收到其他与投资活动有关的现金",B5,"0") -> 0 | AJ5: =IF(C5="投资支付现金",A5,"0") -> 0 | AK5: =IF(C5="投资支付现金",B5,"0") -> 0 | AL5: =IF(C5="购建固定资产、无形资产和其他长期资产支付的现金",A5,"0") -> 0 | AM5: =IF(C5="购建固定资产、无形资产和其他长期资产支付的现金",B5,"0") -> 0 | AN5: =IF(C5="吸收投资收到的现金",A5,"0") -> 0 | AO5: =IF(C5="吸收投资收到的现金",B5,"0") -> 0 | AP5: =IF(C5="取得借款收到的现金",A5,"0") -> 0 | AQ5: =IF(C5="取得借款收到的现金",B5,"0") -> 0 | AR5: =IF(C5="收到其他与筹资活动有关的现金",A5,"0") -> 0 | AS5: =IF(C5="收到其他与筹资活动有关的现金",B5,"0") -> 0 | AT5: =IF(C5="偿还债务支付的现金",A5,"0") -> 0 | AU5: =IF(C5="偿还债务支付的现金",B5,"0") -> 0 | AV5: =IF(C5="分配股利、利润或偿付利息支付的现金",A5,"0") -> 0 | AW5: =IF(C5="分配股利、利润或偿付利息支付的现金",B5,"0") -> 0 | AX5: =IF(C5="支付其他与筹资活动有关的现金",A5,"0") -> 0 | AY5: =IF(C5="支付其他与筹资活动有关的现金",B5,"0") -> 0
H6: =IF(C6="取得的销售货物收到的现金",A6,"0") -> 0 | I6: =IF(C6="取得的销售货物收到的现金",B6,"0") -> 0 | J6: =IF(C6="取得的提供服务到的现金",A6,"0") -> 0 | K6: =IF(C6="取得的提供服务到的现金",B6,"0") -> 0 | L6: =IF(C6="收取利息、手续费及佣金的现金",A6,"0") -> 0 | M6: =IF(C6="收取利息、手续费及佣金的现金",B6,"0") -> 0 | N6: =IF(C6="处置交易性金融资产净增加额",A6,"0") -> 0 | O6: =IF(C6="处置交易性金融资产净增加额",B6,"0") -> 0 | P6: =IF(C6="回购业务资金净增加额",A6,"0") -> 0 | Q6: =IF(C6="回购业务资金净增加额",B6,"0") -> 0 | R6: =IF(C6="收到其他与经营活动有关的现金",A6,"0") -> 0 | S6: =IF(C6="收到其他与经营活动有关的现金",B6,"0") -> 0 | T6: =IF(C6="支付给职工以及为职工支付的现金",A6,"0") -> 0 | U6: =IF(C6="支付给职工以及为职工支付的现金",B6,"0") -> 0 | V6: =IF(C6="支付的各项税费",A6,"0") -> 0 | W6: =IF(C6="支付的各项税费",B6,"0") -> 0 | X6: =IF(C6="回购业务资金净减少额",A6,"0") -> 0 | Y6: =IF(C6="回购业务资金净减少额",B6,"0") -> 0 | Z6: =IF(C6="支付其他与经营活动有关的现金",A6,"0") -> 0 | AA6: =IF(C6="支付其他与经营活动有关的现金",B6,"0") -> 0 | AB6: =IF(C6="收回投资收到的现金",A6,"0") -> 0 | AC6: =IF(C6="收回投资收到的现金",B6,"0") -> 0 | AD6: =IF(C6="取得投资收益收到的现金",A6,"0") -> 0 | AE6: =IF(C6="取得投资收益收到的现金",B6,"0") -> 0 | AF6: =IF(C6="处置固定资产、无形资产和其他长期资产收到的现金净额",A6,"0") -> 0 | AG6: =IF(C6="处置固定资产、无形资产和其他长期资产收到的现金净额",B6,"0") -> 0 | AH6: =IF(C6="收到其他与投资活动有关的现金",A6,"0") -> 0 | AI6: =IF(C6="收到其他与投资活动有关的现金",B6,"0") -> 0 | AJ6: =IF(C6="投资支付现金",A6,"0") -> 0 | AK6: =IF(C6="投资支付现金",B6,"0") -> 0 | AL6: =IF(C6="购建固定资产、无形资产和其他长期资产支付的现金",A6,"0") -> 0 | AM6: =IF(C6="购建固定资产、无形资产和其他长期资产支付的现金",B6,"0") -> 0 | AN6: =IF(C6="吸收投资收到的现金",A6,"0") -> 0 | AO6: =IF(C6="吸收投资收到的现金",B6,"0") -> 0 | AP6: =IF(C6="取得借款收到的现金",A6,"0") -> 0 | AQ6: =IF(C6="取得借款收到的现金",B6,"0") -> 0 | AR6: =IF(C6="收到其他与筹资活动有关的现金",A6,"0") -> 0 | AS6: =IF(C6="收到其他与筹资活动有关的现金",B6,"0") -> 0 | AT6: =IF(C6="偿还债务支付的现金",A6,"0") -> 0 | AU6: =IF(C6="偿还债务支付的现金",B6,"0") -> 0 | AV6: =IF(C6="分配股利、利润或偿付利息支付的现金",A6,"0") -> 0 | AW6: =IF(C6="分配股利、利润或偿付利息支付的现金",B6,"0") -> 0 | AX6: =IF(C6="支付其他与筹资活动有关的现金",A6,"0") -> 0 | AY6: =IF(C6="支付其他与筹资活动有关的现金",B6,"0") -> 0
H7: =IF(C7="取得的销售货物收到的现金",A7,"0") -> 0 | I7: =IF(C7="取得的销售货物收到的现金",B7,"0") -> 0 | J7: =IF(C7="取得的提供服务到的现金",A7,"0") -> 0 | K7: =IF(C7="取得的提供服务到的现金",B7,"0") -> 0 | L7: =IF(C7="收取利息、手续费及佣金的现金",A7,"0") -> 0 | M7: =IF(C7="收取利息、手续费及佣金的现金",B7,"0") -> 0 | N7: =IF(C7="处置交易性金融资产净增加额",A7,"0") -> 0 | O7: =IF(C7="处置交易性金融资产净增加额",B7,"0") -> 0 | P7: =IF(C7="回购业务资金净增加额",A7,"0") -> 0 | Q7: =IF(C7="回购业务资金净增加额",B7,"0") -> 0 | R7: =IF(C7="收到其他与经营活动有关的现金",A7,"0") -> 0 | S7: =IF(C7="收到其他与经营活动有关的现金",B7,"0") -> 0 | T7: =IF(C7="支付给职工以及为职工支付的现金",A7,"0") -> 0 | U7: =IF(C7="支付给职工以及为职工支付的现金",B7,"0") -> 0 | V7: =IF(C7="支付的各项税费",A7,"0") -> 0 | W7: =IF(C7="支付的各项税费",B7,"0") -> 0 | X7: =IF(C7="回购业务资金净减少额",A7,"0") -> 0 | Y7: =IF(C7="回购业务资金净减少额",B7,"0") -> 0 | Z7: =IF(C7="支付其他与经营活动有关的现金",A7,"0") -> 0 | AA7: =IF(C7="支付其他与经营活动有关的现金",B7,"0") -> 0 | AB7: =IF(C7="收回投资收到的现金",A7,"0") -> 0 | AC7: =IF(C7="收回投资收到的现金",B7,"0") -> 0 | AD7: =IF(C7="取得投资收益收到的现金",A7,"0") -> 0 | AE7: =IF(C7="取得投资收益收到的现金",B7,"0") -> 0 | AF7: =IF(C7="处置固定资产、无形资产和其他长期资产收到的现金净额",A7,"0") -> 0 | AG7: =IF(C7="处置固定资产、无形资产和其他长期资产收到的现金净额",B7,"0") -> 0 | AH7: =IF(C7="收到其他与投资活动有关的现金",A7,"0") -> 0 | AI7: =IF(C7="收到其他与投资活动有关的现金",B7,"0") -> 0 | AJ7: =IF(C7="投资支付现金",A7,"0") -> 0 | AK7: =IF(C7="投资支付现金",B7,"0") -> 0 | AL7: =IF(C7="购建固定资产、无形资产和其他长期资产支付的现金",A7,"0") -> 0 | AM7: =IF(C7="购建固定资产、无形资产和其他长期资产支付的现金",B7,"0") -> 0 | AN7: =IF(C7="吸收投资收到的现金",A7,"0") -> 0 | AO7: =IF(C7="吸收投资收到的现金",B7,"0") -> 0 | AP7: =IF(C7="取得借款收到的现金",A7,"0") -> 0 | AQ7: =IF(C7="取得借款收到的现金",B7,"0") -> 0 | AR7: =IF(C7="收到其他与筹资活动有关的现金",A7,"0") -> 0 | AS7: =IF(C7="收到其他与筹资活动有关的现金",B7,"0") -> 0 | AT7: =IF(C7="偿还债务支付的现金",A7,"0") -> 0 | AU7: =IF(C7="偿还债务支付的现金",B7,"0") -> 0 | AV7: =IF(C7="分配股利、利润或偿付利息支付的现金",A7,"0") -> 0 | AW7: =IF(C7="分配股利、利润或偿付利息支付的现金",B7,"0") -> 0 | AX7: =IF(C7="支付其他与筹资活动有关的现金",A7,"0") -> 0 | AY7: =IF(C7="支付其他与筹资活动有关的现金",B7,"0") -> 0
H8: =IF(C8="取得的销售货物收到的现金",A8,"0") -> 0 | I8: =IF(C8="取得的销售货物收到的现金",B8,"0") -> 0 | J8: =IF(C8="取得的提供服务到的现金",A8,"0") -> 0 | K8: =IF(C8="取得的提供服务到的现金",B8,"0") -> 0 | L8: =IF(C8="收取利息、手续费及佣金的现金",A8,"0") -> 0 | M8: =IF(C8="收取利息、手续费及佣金的现金",B8,"0") -> 0 | N8: =IF(C8="处置交易性金融资产净增加额",A8,"0") -> 0 | O8: =IF(C8="处置交易性金融资产净增加额",B8,"0") -> 0 | P8: =IF(C8="回购业务资金净增加额",A8,"0") -> 0 | Q8: =IF(C8="回购业务资金净增加额",B8,"0") -> 0 | R8: =IF(C8="收到其他与经营活动有关的现金",A8,"0") -> 0 | S8: =IF(C8="收到其他与经营活动有关的现金",B8,"0") -> 0 | T8: =IF(C8="支付给职工以及为职工支付的现金",A8,"0") -> 0 | U8: =IF(C8="支付给职工以及为职工支付的现金",B8,"0") -> 0 | V8: =IF(C8="支付的各项税费",A8,"0") -> 0 | W8: =IF(C8="支付的各项税费",B8,"0") -> 0 | X8: =IF(C8="回购业务资金净减少额",A8,"0") -> 0 | Y8: =IF(C8="回购业务资金净减少额",B8,"0") -> 0 | Z8: =IF(C8="支付其他与经营活动有关的现金",A8,"0") -> 0 | AA8: =IF(C8="支付其他与经营活动有关的现金",B8,"0") -> 0 | AB8: =IF(C8="收回投资收到的现金",A8,"0") -> 0 | AC8: =IF(C8="收回投资收到的现金",B8,"0") -> 0 | AD8: =IF(C8="取得投资收益收到的现金",A8,"0") -> 0 | AE8: =IF(C8="取得投资收益收到的现金",B8,"0") -> 0 | AF8: =IF(C8="处置固定资产、无形资产和其他长期资产收到的现金净额",A8,"0") -> 0 | AG8: =IF(C8="处置固定资产、无形资产和其他长期资产收到的现金净额",B8,"0") -> 0 | AH8: =IF(C8="收到其他与投资活动有关的现金",A8,"0") -> 0 | AI8: =IF(C8="收到其他与投资活动有关的现金",B8,"0") -> 0 | AJ8: =IF(C8="投资支付现金",A8,"0") -> 0 | AK8: =IF(C8="投资支付现金",B8,"0") -> 0 | AL8: =IF(C8="购建固定资产、无形资产和其他长期资产支付的现金",A8,"0") -> 0 | AM8: =IF(C8="购建固定资产、无形资产和其他长期资产支付的现金",B8,"0") -> 0 | AN8: =IF(C8="吸收投资收到的现金",A8,"0") -> 0 | AO8: =IF(C8="吸收投资收到的现金",B8,"0") -> 0 | AP8: =IF(C8="取得借款收到的现金",A8,"0") -> 0 | AQ8: =IF(C8="取得借款收到的现金",B8,"0") -> 0 | AR8: =IF(C8="收到其他与筹资活动有关的现金",A8,"0") -> 0 | AS8: =IF(C8="收到其他与筹资活动有关的现金",B8,"0") -> 0 | AT8: =IF(C8="偿还债务支付的现金",A8,"0") -> 0 | AU8: =IF(C8="偿还债务支付的现金",B8,"0") -> 0 | AV8: =IF(C8="分配股利、利润或偿付利息支付的现金",A8,"0") -> 0 | AW8: =IF(C8="分配股利、利润或偿付利息支付的现金",B8,"0") -> 0 | AX8: =IF(C8="支付其他与筹资活动有关的现金",A8,"0") -> 0 | AY8: =IF(C8="支付其他与筹资活动有关的现金",B8,"0") -> 0
H9: =IF(C9="取得的销售货物收到的现金",A9,"0") -> 0 | I9: =IF(C9="取得的销售货物收到的现金",B9,"0") -> 0 | J9: =IF(C9="取得的提供服务到的现金",A9,"0") -> 0 | K9: =IF(C9="取得的提供服务到的现金",B9,"0") -> 0 | L9: =IF(C9="收取利息、手续费及佣金的现金",A9,"0") -> 0 | M9: =IF(C9="收取利息、手续费及佣金的现金",B9,"0") -> 0 | N9: =IF(C9="处置交易性金融资产净增加额",A9,"0") -> 0 | O9: =IF(C9="处置交易性金融资产净增加额",B9,"0") -> 0 | P9: =IF(C9="回购业务资金净增加额",A9,"0") -> 0 | Q9: =IF(C9="回购业务资金净增加额",B9,"0") -> 0 | R9: =IF(C9="收到其他与经营活动有关的现金",A9,"0") -> 0 | S9: =IF(C9="收到其他与经营活动有关的现金",B9,"0") -> 0 | T9: =IF(C9="支付给职工以及为职工支付的现金",A9,"0") -> 0 | U9: =IF(C9="支付给职工以及为职工支付的现金",B9,"0") -> 0 | V9: =IF(C9="支付的各项税费",A9,"0") -> 0 | W9: =IF(C9="支付的各项税费",B9,"0") -> 0 | X9: =IF(C9="回购业务资金净减少额",A9,"0") -> 0 | Y9: =IF(C9="回购业务资金净减少额",B9,"0") -> 0 | Z9: =IF(C9="支付其他与经营活动有关的现金",A9,"0") -> 0 | AA9: =IF(C9="支付其他与经营活动有关的现金",B9,"0") -> 0 | AB9: =IF(C9="收回投资收到的现金",A9,"0") -> 0 | AC9: =IF(C9="收回投资收到的现金",B9,"0") -> 0 | AD9: =IF(C9="取得投资收益收到的现金",A9,"0") -> 0 | AE9: =IF(C9="取得投资收益收到的现金",B9,"0") -> 0 | AF9: =IF(C9="处置固定资产、无形资产和其他长期资产收到的现金净额",A9,"0") -> 0 | AG9: =IF(C9="处置固定资产、无形资产和其他长期资产收到的现金净额",B9,"0") -> 0 | AH9: =IF(C9="收到其他与投资活动有关的现金",A9,"0") -> 0 | AI9: =IF(C9="收到其他与投资活动有关的现金",B9,"0") -> 0 | AJ9: =IF(C9="投资支付现金",A9,"0") -> 0 | AK9: =IF(C9="投资支付现金",B9,"0") -> 0 | AL9: =IF(C9="购建固定资产、无形资产和其他长期资产支付的现金",A9,"0") -> 0 | AM9: =IF(C9="购建固定资产、无形资产和其他长期资产支付的现金",B9,"0") -> 0 | AN9: =IF(C9="吸收投资收到的现金",A9,"0") -> 0 | AO9: =IF(C9="吸收投资收到的现金",B9,"0") -> 0 | AP9: =IF(C9="取得借款收到的现金",A9,"0") -> 0 | AQ9: =IF(C9="取得借款收到的现金",B9,"0") -> 0 | AR9: =IF(C9="收到其他与筹资活动有关的现金",A9,"0") -> 0 | AS9: =IF(C9="收到其他与筹资活动有关的现金",B9,"0") -> 0 | AT9: =IF(C9="偿还债务支付的现金",A9,"0") -> 0 | AU9: =IF(C9="偿还债务支付的现金",B9,"0") -> 0 | AV9: =IF(C9="分配股利、利润或偿付利息支付的现金",A9,"0") -> 0 | AW9: =IF(C9="分配股利、利润或偿付利息支付的现金",B9,"0") -> 0 | AX9: =IF(C9="支付其他与筹资活动有关的现金",A9,"0") -> 0 | AY9: =IF(C9="支付其他与筹资活动有关的现金",B9,"0") -> 0
H10: =IF(C10="取得的销售货物收到的现金",A10,"0") -> 0 | I10: =IF(C10="取得的销售货物收到的现金",B10,"0") -> 0 | J10: =IF(C10="取得的提供服务到的现金",A10,"0") -> 0 | K10: =IF(C10="取得的提供服务到的现金",B10,"0") -> 0 | L10: =IF(C10="收取利息、手续费及佣金的现金",A10,"0") -> 0 | M10: =IF(C10="收取利息、手续费及佣金的现金",B10,"0") -> 0 | N10: =IF(C10="处置交易性金融资产净增加额",A10,"0") -> 0 | O10: =IF(C10="处置交易性金融资产净增加额",B10,"0") -> 0 | P10: =IF(C10="回购业务资金净增加额",A10,"0") -> 0 | Q10: =IF(C10="回购业务资金净增加额",B10,"0") -> 0 | R10: =IF(C10="收到其他与经营活动有关的现金",A10,"0") -> 0 | S10: =IF(C10="收到其他与经营活动有关的现金",B10,"0") -> 0 | T10: =IF(C10="支付给职工以及为职工支付的现金",A10,"0") -> 0 | U10: =IF(C10="支付给职工以及为职工支付的现金",B10,"0") -> 0 | V10: =IF(C10="支付的各项税费",A10,"0") -> 0 | W10: =IF(C10="支付的各项税费",B10,"0") -> 0 | X10: =IF(C10="回购业务资金净减少额",A10,"0") -> 0 | Y10: =IF(C10="回购业务资金净减少额",B10,"0") -> 0 | Z10: =IF(C10="支付其他与经营活动有关的现金",A10,"0") -> 0 | AA10: =IF(C10="支付其他与经营活动有关的现金",B10,"0") -> 0 | AB10: =IF(C10="收回投资收到的现金",A10,"0") -> 0 | AC10: =IF(C10="收回投资收到的现金",B10,"0") -> 0 | AD10: =IF(C10="取得投资收益收到的现金",A10,"0") -> 0 | AE10: =IF(C10="取得投资收益收到的现金",B10,"0") -> 0 | AF10: =IF(C10="处置固定资产、无形资产和其他长期资产收到的现金净额",A10,"0") -> 0 | AG10: =IF(C10="处置固定资产、无形资产和其他长期资产收到的现金净额",B10,"0") -> 0 | AH10: =IF(C10="收到其他与投资活动有关的现金",A10,"0") -> 0 | AI10: =IF(C10="收到其他与投资活动有关的现金",B10,"0") -> 0 | AJ10: =IF(C10="投资支付现金",A10,"0") -> 0 | AK10: =IF(C10="投资支付现金",B10,"0") -> 0 | AL10: =IF(C10="购建固定资产、无形资产和其他长期资产支付的现金",A10,"0") -> 0 | AM10: =IF(C10="购建固定资产、无形资产和其他长期资产支付的现金",B10,"0") -> 0 | AN10: =IF(C10="吸收投资收到的现金",A10,"0") -> 0 | AO10: =IF(C10="吸收投资收到的现金",B10,"0") -> 0 | AP10: =IF(C10="取得借款收到的现金",A10,"0") -> 0 | AQ10: =IF(C10="取得借款收到的现金",B10,"0") -> 0 | AR10: =IF(C10="收到其他与筹资活动有关的现金",A10,"0") -> 0 | AS10: =IF(C10="收到其他与筹资活动有关的现金",B10,"0") -> 0 | AT10: =IF(C10="偿还债务支付的现金",A10,"0") -> 0 | AU10: =IF(C10="偿还债务支付的现金",B10,"0") -> 0 | AV10: =IF(C10="分配股利、利润或偿付利息支付的现金",A10,"0") -> 0 | AW10: =IF(C10="分配股利、利润或偿付利息支付的现金",B10,"0") -> 0 | AX10: =IF(C10="支付其他与筹资活动有关的现金",A10,"0") -> 0 | AY10: =IF(C10="支付其他与筹资活动有关的现金",B10,"0") -> 0
H11: =IF(C11="取得的销售货物收到的现金",A11,"0") -> 0 | I11: =IF(C11="取得的销售货物收到的现金",B11,"0") -> 0 | J11: =IF(C11="取得的提供服务到的现金",A11,"0") -> 0 | K11: =IF(C11="取得的提供服务到的现金",B11,"0") -> 0 | L11: =IF(C11="收取利息、手续费及佣金的现金",A11,"0") -> 0 | M11: =IF(C11="收取利息、手续费及佣金的现金",B11,"0") -> 0 | N11: =IF(C11="处置交易性金融资产净增加额",A11,"0") -> 0 | O11: =IF(C11="处置交易性金融资产净增加额",B11,"0") -> 0 | P11: =IF(C11="回购业务资金净增加额",A11,"0") -> 0 | Q11: =IF(C11="回购业务资金净增加额",B11,"0") -> 0 | R11: =IF(C11="收到其他与经营活动有关的现金",A11,"0") -> 0 | S11: =IF(C11="收到其他与经营活动有关的现金",B11,"0") -> 0 | T11: =IF(C11="支付给职工以及为职工支付的现金",A11,"0") -> 0 | U11: =IF(C11="支付给职工以及为职工支付的现金",B11,"0") -> 0 | V11: =IF(C11="支付的各项税费",A11,"0") -> 0 | W11: =IF(C11="支付的各项税费",B11,"0") -> 0 | X11: =IF(C11="回购业务资金净减少额",A11,"0") -> 0 | Y11: =IF(C11="回购业务资金净减少额",B11,"0") -> 0 | Z11: =IF(C11="支付其他与经营活动有关的现金",A11,"0") -> 0 | AA11: =IF(C11="支付其他与经营活动有关的现金",B11,"0") -> 0 | AB11: =IF(C11="收回投资收到的现金",A11,"0") -> 0 | AC11: =IF(C11="收回投资收到的现金",B11,"0") -> 0 | AD11: =IF(C11="取得投资收益收到的现金",A11,"0") -> 0 | AE11: =IF(C11="取得投资收益收到的现金",B11,"0") -> 0 | AF11: =IF(C11="处置固定资产、无形资产和其他长期资产收到的现金净额",A11,"0") -> 0 | AG11: =IF(C11="处置固定资产、无形资产和其他长期资产收到的现金净额",B11,"0") -> 0 | AH11: =IF(C11="收到其他与投资活动有关的现金",A11,"0") -> 0 | AI11: =IF(C11="收到其他与投资活动有关的现金",B11,"0") -> 0 | AJ11: =IF(C11="投资支付现金",A11,"0") -> 0 | AK11: =IF(C11="投资支付现金",B11,"0") -> 0 | AL11: =IF(C11="购建固定资产、无形资产和其他长期资产支付的现金",A11,"0") -> 0 | AM11: =IF(C11="购建固定资产、无形资产和其他长期资产支付的现金",B11,"0") -> 0 | AN11: =IF(C11="吸收投资收到的现金",A11,"0") -> 0 | AO11: =IF(C11="吸收投资收到的现金",B11,"0") -> 0 | AP11: =IF(C11="取得借款收到的现金",A11,"0") -> 0 | AQ11: =IF(C11="取得借款收到的现金",B11,"0") -> 0 | AR11: =IF(C11="收到其他与筹资活动有关的现金",A11,"0") -> 0 | AS11: =IF(C11="收到其他与筹资活动有关的现金",B11,"0") -> 0 | AT11: =IF(C11="偿还债务支付的现金",A11,"0") -> 0 | AU11: =IF(C11="偿还债务支付的现金",B11,"0") -> 0 | AV11: =IF(C11="分配股利、利润或偿付利息支付的现金",A11,"0") -> 0 | AW11: =IF(C11="分配股利、利润或偿付利息支付的现金",B11,"0") -> 0 | AX11: =IF(C11="支付其他与筹资活动有关的现金",A11,"0") -> 0 | AY11: =IF(C11="支付其他与筹资活动有关的现金",B11,"0") -> 0
H12: =IF(C12="取得的销售货物收到的现金",A12,"0") -> 0 | I12: =IF(C12="取得的销售货物收到的现金",B12,"0") -> 0 | J12: =IF(C12="取得的提供服务到的现金",A12,"0") -> 0 | K12: =IF(C12="取得的提供服务到的现金",B12,"0") -> 0 | L12: =IF(C12="收取利息、手续费及佣金的现金",A12,"0") -> 0 | M12: =IF(C12="收取利息、手续费及佣金的现金",B12,"0") -> 0 | N12: =IF(C12="处置交易性金融资产净增加额",A12,"0") -> 0 | O12: =IF(C12="处置交易性金融资产净增加额",B12,"0") -> 0 | P12: =IF(C12="回购业务资金净增加额",A12,"0") -> 0 | Q12: =IF(C12="回购业务资金净增加额",B12,"0") -> 0 | R12: =IF(C12="收到其他与经营活动有关的现金",A12,"0") -> 0 | S12: =IF(C12="收到其他与经营活动有关的现金",B12,"0") -> 0 | T12: =IF(C12="支付给职工以及为职工支付的现金",A12,"0") -> 0 | U12: =IF(C12="支付给职工以及为职工支付的现金",B12,"0") -> 0 | V12: =IF(C12="支付的各项税费",A12,"0") -> 0 | W12: =IF(C12="支付的各项税费",B12,"0") -> 0 | X12: =IF(C12="回购业务资金净减少额",A12,"0") -> 0 | Y12: =IF(C12="回购业务资金净减少额",B12,"0") -> 0 | Z12: =IF(C12="支付其他与经营活动有关的现金",A12,"0") -> 0 | AA12: =IF(C12="支付其他与经营活动有关的现金",B12,"0") -> 0 | AB12: =IF(C12="收回投资收到的现金",A12,"0") -> 0 | AC12: =IF(C12="收回投资收到的现金",B12,"0") -> 0 | AD12: =IF(C12="取得投资收益收到的现金",A12,"0") -> 0 | AE12: =IF(C12="取得投资收益收到的现金",B12,"0") -> 0 | AF12: =IF(C12="处置固定资产、无形资产和其他长期资产收到的现金净额",A12,"0") -> 0 | AG12: =IF(C12="处置固定资产、无形资产和其他长期资产收到的现金净额",B12,"0") -> 0 | AH12: =IF(C12="收到其他与投资活动有关的现金",A12,"0") -> 0 | AI12: =IF(C12="收到其他与投资活动有关的现金",B12,"0") -> 0 | AJ12: =IF(C12="投资支付现金",A12,"0") -> 0 | AK12: =IF(C12="投资支付现金",B12,"0") -> 0 | AL12: =IF(C12="购建固定资产、无形资产和其他长期资产支付的现金",A12,"0") -> 0 | AM12: =IF(C12="购建固定资产、无形资产和其他长期资产支付的现金",B12,"0") -> 0 | AN12: =IF(C12="吸收投资收到的现金",A12,"0") -> 0 | AO12: =IF(C12="吸收投资收到的现金",B12,"0") -> 0 | AP12: =IF(C12="取得借款收到的现金",A12,"0") -> 0 | AQ12: =IF(C12="取得借款收到的现金",B12,"0") -> 0 | AR12: =IF(C12="收到其他与筹资活动有关的现金",A12,"0") -> 0 | AS12: =IF(C12="收到其他与筹资活动有关的现金",B12,"0") -> 0 | AT12: =IF(C12="偿还债务支付的现金",A12,"0") -> 0 | AU12: =IF(C12="偿还债务支付的现金",B12,"0") -> 0 | AV12: =IF(C12="分配股利、利润或偿付利息支付的现金",A12,"0") -> 0 | AW12: =IF(C12="分配股利、利润或偿付利息支付的现金",B12,"0") -> 0 | AX12: =IF(C12="支付其他与筹资活动有关的现金",A12,"0") -> 0 | AY12: =IF(C12="支付其他与筹资活动有关的现金",B12,"0") -> 0
H13: =IF(C13="取得的销售货物收到的现金",A13,"0") -> 0 | I13: =IF(C13="取得的销售货物收到的现金",B13,"0") -> 0 | J13: =IF(C13="取得的提供服务到的现金",A13,"0") -> 0 | K13: =IF(C13="取得的提供服务到的现金",B13,"0") -> 0 | L13: =IF(C13="收取利息、手续费及佣金的现金",A13,"0") -> 0 | M13: =IF(C13="收取利息、手续费及佣金的现金",B13,"0") -> 0 | N13: =IF(C13="处置交易性金融资产净增加额",A13,"0") -> 0 | O13: =IF(C13="处置交易性金融资产净增加额",B13,"0") -> 0 | P13: =IF(C13="回购业务资金净增加额",A13,"0") -> 0 | Q13: =IF(C13="回购业务资金净增加额",B13,"0") -> 0 | R13: =IF(C13="收到其他与经营活动有关的现金",A13,"0") -> 0 | S13: =IF(C13="收到其他与经营活动有关的现金",B13,"0") -> 0 | T13: =IF(C13="支付给职工以及为职工支付的现金",A13,"0") -> 0 | U13: =IF(C13="支付给职工以及为职工支付的现金",B13,"0") -> 0 | V13: =IF(C13="支付的各项税费",A13,"0") -> 0 | W13: =IF(C13="支付的各项税费",B13,"0") -> 0 | X13: =IF(C13="回购业务资金净减少额",A13,"0") -> 0 | Y13: =IF(C13="回购业务资金净减少额",B13,"0") -> 0 | Z13: =IF(C13="支付其他与经营活动有关的现金",A13,"0") -> 0 | AA13: =IF(C13="支付其他与经营活动有关的现金",B13,"0") -> 0 | AB13: =IF(C13="收回投资收到的现金",A13,"0") -> 0 | AC13: =IF(C13="收回投资收到的现金",B13,"0") -> 0 | AD13: =IF(C13="取得投资收益收到的现金",A13,"0") -> 0 | AE13: =IF(C13="取得投资收益收到的现金",B13,"0") -> 0 | AF13: =IF(C13="处置固定资产、无形资产和其他长期资产收到的现金净额",A13,"0") -> 0 | AG13: =IF(C13="处置固定资产、无形资产和其他长期资产收到的现金净额",B13,"0") -> 0 | AH13: =IF(C13="收到其他与投资活动有关的现金",A13,"0") -> 0 | AI13: =IF(C13="收到其他与投资活动有关的现金",B13,"0") -> 0 | AJ13: =IF(C13="投资支付现金",A13,"0") -> 0 | AK13: =IF(C13="投资支付现金",B13,"0") -> 0 | AL13: =IF(C13="购建固定资产、无形资产和其他长期资产支付的现金",A13,"0") -> 0 | AM13: =IF(C13="购建固定资产、无形资产和其他长期资产支付的现金",B13,"0") -> 0 | AN13: =IF(C13="吸收投资收到的现金",A13,"0") -> 0 | AO13: =IF(C13="吸收投资收到的现金",B13,"0") -> 0 | AP13: =IF(C13="取得借款收到的现金",A13,"0") -> 0 | AQ13: =IF(C13="取得借款收到的现金",B13,"0") -> 0 | AR13: =IF(C13="收到其他与筹资活动有关的现金",A13,"0") -> 0 | AS13: =IF(C13="收到其他与筹资活动有关的现金",B13,"0") -> 0 | AT13: =IF(C13="偿还债务支付的现金",A13,"0") -> 0 | AU13: =IF(C13="偿还债务支付的现金",B13,"0") -> 0 | AV13: =IF(C13="分配股利、利润或偿付利息支付的现金",A13,"0") -> 0 | AW13: =IF(C13="分配股利、利润或偿付利息支付的现金",B13,"0") -> 0 | AX13: =IF(C13="支付其他与筹资活动有关的现金",A13,"0") -> 0 | AY13: =IF(C13="支付其他与筹资活动有关的现金",B13,"0") -> 0
H14: =IF(C14="取得的销售货物收到的现金",A14,"0") -> 0 | I14: =IF(C14="取得的销售货物收到的现金",B14,"0") -> 0 | J14: =IF(C14="取得的提供服务到的现金",A14,"0") -> 0 | K14: =IF(C14="取得的提供服务到的现金",B14,"0") -> 0 | L14: =IF(C14="收取利息、手续费及佣金的现金",A14,"0") -> 0 | M14: =IF(C14="收取利息、手续费及佣金的现金",B14,"0") -> 0 | N14: =IF(C14="处置交易性金融资产净增加额",A14,"0") -> 0 | O14: =IF(C14="处置交易性金融资产净增加额",B14,"0") -> 0 | P14: =IF(C14="回购业务资金净增加额",A14,"0") -> 0 | Q14: =IF(C14="回购业务资金净增加额",B14,"0") -> 0 | R14: =IF(C14="收到其他与经营活动有关的现金",A14,"0") -> 0 | S14: =IF(C14="收到其他与经营活动有关的现金",B14,"0") -> 0 | T14: =IF(C14="支付给职工以及为职工支付的现金",A14,"0") -> 0 | U14: =IF(C14="支付给职工以及为职工支付的现金",B14,"0") -> 0 | V14: =IF(C14="支付的各项税费",A14,"0") -> 0 | W14: =IF(C14="支付的各项税费",B14,"0") -> 0 | X14: =IF(C14="回购业务资金净减少额",A14,"0") -> 0 | Y14: =IF(C14="回购业务资金净减少额",B14,"0") -> 0 | Z14: =IF(C14="支付其他与经营活动有关的现金",A14,"0") -> 0 | AA14: =IF(C14="支付其他与经营活动有关的现金",B14,"0") -> 0 | AB14: =IF(C14="收回投资收到的现金",A14,"0") -> 0 | AC14: =IF(C14="收回投资收到的现金",B14,"0") -> 0 | AD14: =IF(C14="取得投资收益收到的现金",A14,"0") -> 0 | AE14: =IF(C14="取得投资收益收到的现金",B14,"0") -> 0 | AF14: =IF(C14="处置固定资产、无形资产和其他长期资产收到的现金净额",A14,"0") -> 0 | AG14: =IF(C14="处置固定资产、无形资产和其他长期资产收到的现金净额",B14,"0") -> 0 | AH14: =IF(C14="收到其他与投资活动有关的现金",A14,"0") -> 0 | AI14: =IF(C14="收到其他与投资活动有关的现金",B14,"0") -> 0 | AJ14: =IF(C14="投资支付现金",A14,"0") -> 0 | AK14: =IF(C14="投资支付现金",B14,"0") -> 0 | AL14: =IF(C14="购建固定资产、无形资产和其他长期资产支付的现金",A14,"0") -> 0 | AM14: =IF(C14="购建固定资产、无形资产和其他长期资产支付的现金",B14,"0") -> 0 | AN14: =IF(C14="吸收投资收到的现金",A14,"0") -> 0 | AO14: =IF(C14="吸收投资收到的现金",B14,"0") -> 0 | AP14: =IF(C14="取得借款收到的现金",A14,"0") -> 0 | AQ14: =IF(C14="取得借款收到的现金",B14,"0") -> 0 | AR14: =IF(C14="收到其他与筹资活动有关的现金",A14,"0") -> 0 | AS14: =IF(C14="收到其他与筹资活动有关的现金",B14,"0") -> 0 | AT14: =IF(C14="偿还债务支付的现金",A14,"0") -> 0 | AU14: =IF(C14="偿还债务支付的现金",B14,"0") -> 0 | AV14: =IF(C14="分配股利、利润或偿付利息支付的现金",A14,"0") -> 0 | AW14: =IF(C14="分配股利、利润或偿付利息支付的现金",B14,"0") -> 0 | AX14: =IF(C14="支付其他与筹资活动有关的现金",A14,"0") -> 0 | AY14: =IF(C14="支付其他与筹资活动有关的现金",B14,"0") -> 0
H15: =IF(C15="取得的销售货物收到的现金",A15,"0") -> 0 | I15: =IF(C15="取得的销售货物收到的现金",B15,"0") -> 0 | J15: =IF(C15="取得的提供服务到的现金",A15,"0") -> 0 | K15: =IF(C15="取得的提供服务到的现金",B15,"0") -> 0 | L15: =IF(C15="收取利息、手续费及佣金的现金",A15,"0") -> 0 | M15: =IF(C15="收取利息、手续费及佣金的现金",B15,"0") -> 0 | N15: =IF(C15="处置交易性金融资产净增加额",A15,"0") -> 0 | O15: =IF(C15="处置交易性金融资产净增加额",B15,"0") -> 0 | P15: =IF(C15="回购业务资金净增加额",A15,"0") -> 0 | Q15: =IF(C15="回购业务资金净增加额",B15,"0") -> 0 | R15: =IF(C15="收到其他与经营活动有关的现金",A15,"0") -> 0 | S15: =IF(C15="收到其他与经营活动有关的现金",B15,"0") -> 0 | T15: =IF(C15="支付给职工以及为职工支付的现金",A15,"0") -> 0 | U15: =IF(C15="支付给职工以及为职工支付的现金",B15,"0") -> 0 | V15: =IF(C15="支付的各项税费",A15,"0") -> 0 | W15: =IF(C15="支付的各项税费",B15,"0") -> 0 | X15: =IF(C15="回购业务资金净减少额",A15,"0") -> 0 | Y15: =IF(C15="回购业务资金净减少额",B15,"0") -> 0 | Z15: =IF(C15="支付其他与经营活动有关的现金",A15,"0") -> 0 | AA15: =IF(C15="支付其他与经营活动有关的现金",B15,"0") -> 0 | AB15: =IF(C15="收回投资收到的现金",A15,"0") -> 0 | AC15: =IF(C15="收回投资收到的现金",B15,"0") -> 0 | AD15: =IF(C15="取得投资收益收到的现金",A15,"0") -> 0 | AE15: =IF(C15="取得投资收益收到的现金",B15,"0") -> 0 | AF15: =IF(C15="处置固定资产、无形资产和其他长期资产收到的现金净额",A15,"0") -> 0 | AG15: =IF(C15="处置固定资产、无形资产和其他长期资产收到的现金净额",B15,"0") -> 0 | AH15: =IF(C15="收到其他与投资活动有关的现金",A15,"0") -> 0 | AI15: =IF(C15="收到其他与投资活动有关的现金",B15,"0") -> 0 | AJ15: =IF(C15="投资支付现金",A15,"0") -> 0 | AK15: =IF(C15="投资支付现金",B15,"0") -> 0 | AL15: =IF(C15="购建固定资产、无形资产和其他长期资产支付的现金",A15,"0") -> 0 | AM15: =IF(C15="购建固定资产、无形资产和其他长期资产支付的现金",B15,"0") -> 0 | AN15: =IF(C15="吸收投资收到的现金",A15,"0") -> 0 | AO15: =IF(C15="吸收投资收到的现金",B15,"0") -> 0 | AP15: =IF(C15="取得借款收到的现金",A15,"0") -> 0 | AQ15: =IF(C15="取得借款收到的现金",B15,"0") -> 0 | AR15: =IF(C15="收到其他与筹资活动有关的现金",A15,"0") -> 0 | AS15: =IF(C15="收到其他与筹资活动有关的现金",B15,"0") -> 0 | AT15: =IF(C15="偿还债务支付的现金",A15,"0") -> 0 | AU15: =IF(C15="偿还债务支付的现金",B15,"0") -> 0 | AV15: =IF(C15="分配股利、利润或偿付利息支付的现金",A15,"0") -> 0 | AW15: =IF(C15="分配股利、利润或偿付利息支付的现金",B15,"0") -> 0 | AX15: =IF(C15="支付其他与筹资活动有关的现金",A15,"0") -> 0 | AY15: =IF(C15="支付其他与筹资活动有关的现金",B15,"0") -> 0
... H50: =IF(C50="取得的销售货物收到的现金",A50,"0") -> 0 | I50: =IF(C50="取得的销售货物收到的现金",B50,"0") -> 0 | J50: =IF(C50="取得的提供服务到的现金",A50,"0") -> 0 | K50: =IF(C50="取得的提供服务到的现金",B50,"0") -> 0 | L50: =IF(C50="收取利息、手续费及佣金的现金",A50,"0") -> 0 | M50: =IF(C50="收取利息、手续费及佣金的现金",B50,"0") -> 0 | N50: =IF(C50="处置交易性金融资产净增加额",A50,"0") -> 0 | O50: =IF(C50="处置交易性金融资产净增加额",B50,"0") -> 0 | P50: =IF(C50="回购业务资金净增加额",A50,"0") -> 0 | Q50: =IF(C50="回购业务资金净增加额",B50,"0") -> 0 | R50: =IF(C50="收到其他与经营活动有关的现金",A50,"0") -> 0 | S50: =IF(C50="收到其他与经营活动有关的现金",B50,"0") -> 0 | T50: =IF(C50="支付给职工以及为职工支付的现金",A50,"0") -> 0 | U50: =IF(C50="支付给职工以及为职工支付的现金",B50,"0") -> 0 | V50: =IF(C50="支付的各项税费",A50,"0") -> 0 | W50: =IF(C50="支付的各项税费",B50,"0") -> 0 | X50: =IF(C50="回购业务资金净减少额",A50,"0") -> 0 | Y50: =IF(C50="回购业务资金净减少额",B50,"0") -> 0 | Z50: =IF(C50="支付其他与经营活动有关的现金",A50,"0") -> 0 | AA50: =IF(C50="支付其他与经营活动有关的现金",B50,"0") -> 0 | AB50: =IF(C50="收回投资收到的现金",A50,"0") -> 0 | AC50: =IF(C50="收回投资收到的现金",B50,"0") -> 0 | AD50: =IF(C50="取得投资收益收到的现金",A50,"0") -> 0 | AE50: =IF(C50="取得投资收益收到的现金",B50,"0") -> 0 | AF50: =IF(C50="处置固定资产、无形资产和其他长期资产收到的现金净额",A50,"0") -> 0 | AG50: =IF(C50="处置固定资产、无形资产和其他长期资产收到的现金净额",B50,"0") -> 0 | AH50: =IF(C50="收到其他与投资活动有关的现金",A50,"0") -> 0 | AI50: =IF(C50="收到其他与投资活动有关的现金",B50,"0") -> 0 | AJ50: =IF(C50="投资支付现金",A50,"0") -> 0 | AK50: =IF(C50="投资支付现金",B50,"0") -> 0 | AL50: =IF(C50="购建固定资产、无形资产和其他长期资产支付的现金",A50,"0") -> 0 | AM50: =IF(C50="购建固定资产、无形资产和其他长期资产支付的现金",B50,"0") -> 0 | AN50: =IF(C50="吸收投资收到的现金",A50,"0") -> 0 | AO50: =IF(C50="吸收投资收到的现金",B50,"0") -> 0 | AP50: =IF(C50="取得借款收到的现金",A50,"0") -> 0 | AQ50: =IF(C50="取得借款收到的现金",B50,"0") -> 0 | AR50: =IF(C50="收到其他与筹资活动有关的现金",A50,"0") -> 0 | AS50: =IF(C50="收到其他与筹资活动有关的现金",B50,"0") -> 0 | AT50: =IF(C50="偿还债务支付的现金",A50,"0") -> 0 | AU50: =IF(C50="偿还债务支付的现金",B50,"0") -> 0 | AV50: =IF(C50="分配股利、利润或偿付利息支付的现金",A50,"0") -> 0 | AW50: =IF(C50="分配股利、利润或偿付利息支付的现金",B50,"0") -> 0 | AX50: =IF(C50="支付其他与筹资活动有关的现金",A50,"0") -> 0 | AY50: =IF(C50="支付其他与筹资活动有关的现金",B50,"0") -> 0
H51: 增加 | I51: 减少 | J51: 增加 | K51: 减少 | L51: 增加 | M51: 减少 | N51: 增加 | O51: 减少 | P51: 增加 | Q51: 减少 | R51: 增加 | S51: 减少 | T51: 增加 | U51: 减少 | V51: 增加 | W51: 减少 | X51: 增加 | Y51: 减少 | Z51: 增加 | AA51: 减少 | AB51: 增加 | AC51: 减少 | AD51: 增加 | AE51: 减少 | AF51: 增加 | AG51: 减少 | AH51: 增加 | AI51: 减少 | AJ51: 增加 | AK51: 减少 | AL51: 增加 | AM51: 减少 | AN51: 增加 | AO51: 减少 | AP51: 增加 | AQ51: 减少 | AR51: 增加 | AS51: 减少 | AT51: 增加 | AU51: 减少 | AV51: 增加 | AW51: 减少 | AX51: 增加 | AY51: 减少
G52: sum | H52: =SUM(H3:H50) -> 0 | I52: =SUM(I3:I50) -> 0 | J52: =SUM(J3:J50) -> 0 | K52: =SUM(K3:K50) -> 0 | L52: =SUM(L3:L50) -> 0 | M52: =SUM(M3:M50) -> 0 | N52: =SUM(N3:N50) -> 0 | O52: =SUM(O3:O50) -> 0 | ... AY52: =SUM(AY3:AY50) -> 0
I53: 取得的销售货物收到的现金 | K53: 取得的提供服务到的现金 | M53: 收取利息、手续费及佣金的现金 | O53: 处置交易性金融资产净增加额 | Q53: 回购业务资金净增加额 | S53: 收到其他与经营活动有关的现金 | U53: 支付给职工以及为职工支付的现金 | W53: 支付的各项税费 | Y53: 回购业务资金净减少额 | AA53: 支付其他与经营活动有关的现金 | AC53: 收回投资收到的现金 | AE53: 取得投资收益收到的现金 | AG53: 处置固定资产、无形资产和其他长期资产收到的现金净额 | AI53: 收到其他与投资活动有关的现金 | AK53: 投资支付现金 | AM53: 购建固定资产、无形资产和其他长期资产支付的现金 | AO53: 吸收投资收到的现金 | AQ53: 取得借款收到的现金 | AS53: 收到其他与筹资活动有关的现金 | AU53: 偿还债务支付的现金 | AW53: 分配股利、利润或偿付利息支付的现金 | AY53: 支付其他与筹资活动有关的现金

Sheet 现金流量表
A1: 现金流量表
A2: 46204
A3: 编制单位：XX公司
A4: 项目 | B4: 行次 | C4: 本年金额 | D4: 项目 | E4: 行次 | F4: 本年金额
A5: 一、经营活动产生的现金流量： | B5: 1 | D5: 投资支付现金 | E5: 21 | F5: =-(计算!AJ52-计算!AK52) -> 0
A6: 取得的销售货物收到的现金 | B6: 2 | C6: =计算!H52-计算!I52 -> 0 | D6: 购建固定资产、无形资产和其他长期资产支付的现金 | E6: 22 | F6: =-(计算!AL52-计算!AM52) -> 0
A7: 取得的提供服务收到的现金 | B7: 3 | C7: =计算!J52-计算!K52 -> 0 | D7: 投资活动现金流出小计 | E7: 23 | F7: =SUM(F5:F6) -> 0
A8: 收取利息、手续费及佣金的现金 | B8: 4 | C8: =计算!L52-计算!M52 -> 0 | D8: 投资活动产生的现金流量净额 | E8: 24 | F8: =C24-F7 -> 0
A9: 处置交易性金融资产净增加额 | B9: 5 | C9: =计算!N52-计算!O52 -> 0 | D9: 三、筹资活动产生的现金流量： | E9: 25
A10: 回购业务资金净增加额 | B10: 6 | C10: =计算!P52-计算!Q52 -> 0 | D10: 吸收投资收到的现金 | E10: 26 | F10: =计算!AN52-计算!AO52 -> 0
A11: 收到其他与经营活动有关的现金 | B11: 7 | C11: =计算!R52-计算!S52 -> 0 | D11: 其中：子公司吸收少数股东投资收到的现金 | E11: 27
A12: 经营活动现金流入小计 | B12: 8 | C12: =SUM(C6:C11) -> 0 | D12: 取得借款收到的现金 | E12: 28 | F12: =计算!AP52-计算!AQ52 -> 0
A13: 支付给职工以及为职工支付的现金 | B13: 9 | C13: =-(计算!T52-计算!U52) -> 0 | D13: 收到其他与筹资活动有关的现金 | E13: 29 | F13: =计算!AR52-计算!AS52 -> 0
A14: 支付的各项税费 | B14: 10 | C14: =-(计算!V52-计算!W52) -> 0 | D14: 筹资活动现金流入小计 | E14: 30 | F14: =F10+F12+F13 -> 0
A15: 回购业务资金净减少额 | B15: 11 | C15: =-(计算!X52-计算!Y52) -> 0 | D15: 偿还债务支付的现金 | E15: 31 | F15: =-(计算!AT52-计算!AU52) -> 0
A16: 支付其他与经营活动有关的现金 | B16: 12 | C16: =-(计算!Z52-计算!AA52) -> 0 | D16: 分配股利、利润支付的现金 | E16: 32 | F16: =-(计算!AV52-计算!AW52) -> 0
A17: 经营活动现金流出小计 | B17: 13 | C17: =SUM(C13:C16) -> 0 | D17: 其中：子公司支付给少数股东的股利、利润 | E17: 33
A18: 经营活动产生的现金流量净额 | B18: 14 | C18: =C12-C17 -> 0 | D18: 支付其他与筹资活动有关的现金 | E18: 34 | F18: =-(计算!AX52-计算!AY52) -> 0
A19: 二、投资活动产生的现金流量： | B19: 15 | D19: 筹资活动现金流出小计 | E19: 35 | F19: =F15+F16+F18 -> 0
A20: 收回投资收到的现金 | B20: 16 | C20: =计算!AB52-计算!AC52 -> 0 | D20: 筹资活动产生的现金流量净额 | E20: 36 | F20: =F14-F19 -> 0
A21: 取得投资收益收到的现金 | B21: 17 | C21: =计算!AD52-计算!AE52 -> 0 | D21: 四、汇率变动对现金及现金等价物的影响 | E21: 37
A22: 处置固定资产、无形资产和其他长期资产收到的现金净额 | B22: 18 | C22: =计算!AF52-计算!AG52 -> 0 | D22: 五、现金及现金等价物净(减少)/增加额 | E22: 38 | F22: =C18+F20+F8 -> 0
A23: 收到其他与投资活动有关的现金 | B23: 19 | C23: =计算!AH52-计算!AI52 -> 0 | D23: 加：期初现金及现金等价物余额 | E23: 39 | F23: 0
A24: 投资活动现金流入小计 | B24: 20 | C24: =SUM(C20:C23) -> 0 | D24: 六、期末现金及现金等价物余额 | E24: 40 | F24: =F22+F23 -> 0
A25: 法定代表人： | B25: 主管会计工作负责人： | D25: 会计机构负责人： | F25: =F24-银行流水账!F159 -> 0

Sheet 常用财务分析表
A1: 常用财务分析表
A2: 指标意义 | B2: 指标计算公式 | C2: 指标数值 | D2: 备注
A3: 短期偿债能力 | B3: 营运资本=流动资产-流动负债 | C3: =资产负债表!D28-资产负债表!H28 -> 431.76 | D3: 流动资产超过流动负债的部分
B4: 流动比率=流动资产/流动负债 | C4: =资产负债表!D28/资产负债表!H28 -> #DIV/0! | D4: 最常见的反映企业短期偿债能力的指标
B5: 速动比率=速动资产/流动负债 | C5: =(资产负债表!D28-资产负债表!D19-资产负债表!D21)/资产负债表!H28 -> #DIV/0! | D5: 速动资产为扣除存货后的流动资产
B6: 现金比率=（货币资金+交易性金融资产）/流动负债 | C6: =(资产负债表!D8+资产负债表!D9)/资产负债表!H28 -> #DIV/0! | D6: 表示一元流动负债有多少现金作为偿还保障
B7: 现金流动比率=年经营现金净流量/年底流动负债 | C7: =现金流量表!C18/资产负债表!H28 -> #DIV/0!
A8: 长期偿债能力 | B8: 资产负债率=（总负债/总资产）*100% | C8: =资产负债表!H56/资产负债表!D79 -> 0 | D8: 总债务存量比率
B9: 产权比率=（总负债/所有者权益）*100% | C9: =资产负债表!H56/资产负债表!H78*100% -> #DIV/0!
B10: 权益乘数=总资产/所有者权益 | C10: =资产负债表!D79/资产负债表!H78 -> #DIV/0!
B11: 利息保障倍数=息税前利润总额\利息支出 | C11: =(利润表!C35+利润表!C21)/利润表!C21 -> #DIV/0! | D11: 衡量企业偿付借款利息的能力
A12: 运营能力 | B12: 应收账款周转率=营业收入/平均应收账款余额(（期初+期末）/2) | C12: =利润表!C7/资产负债表!D14 -> #DIV/0! | D12: 应收账款一年周转的次数或每1元应收账款投资支持的销售收入
B13: 存货周转率=营业成本/平均存货余额 | C13: =利润表!C7/资产负债表!D19 -> 0 | D13: 存货的周转次数
B14: 流动资产周转率=营业收入/平均流动资产总额 | C14: =利润表!C7/资产负债表!D28 -> 0 | D14: 一个会计年度企业流动资产周转的次数
B15: 非流动资产周转率=营业收入/非流动资产平均总额 | C15: =利润表!C7/(资产负债表!D44+资产负债表!D55+资产负债表!D67+资产负债表!D78) -> #DIV/0!
B16: 总资产周转率=营业收入/平均资产总额 | C16: =利润表!C7/资产负债表!D79 -> 0
A17: 盈利能力 | B17: 销售毛利率=（主营业务利润/销售收入）*100% | C17: =利润表!C18/利润表!C7 -> #DIV/0!
B18: 销售净利率=（净利润/销售收入）*100% | C18: =利润表!C37/利润表!C7 -> #DIV/0!
B19: 资产利润率=（息税前净利润/平均总资产）*100% | C19: =利润表!C35/资产负债表!D79 -> 0
B20: 权益报酬率/净资产收益率=(净利润/股东权益)*100% | C20: =利润表!C37/资产负债表!H78 -> #DIV/0!
B21: 每股收益=净利润/普通股总数 | C21: =利润表!C37/资产负债表!H60 -> #DIV/0!
B22: 每股股利=股利总额/普通股总数 | C22: =(资产负债表!H71-资产负债表!H72)/资产负债表!H60 -> #DIV/0!
B23: 股利发放率=每股股利/每股收益*100% | C23: =C22/C21 -> #DIV/0!
B24: 市盈率（P/E）=普通股每股股价/普通股每股市价
B25: 市净率=每股市场价格/每股净资产
A26: 发展能力 | B26: 营业收入增长率=本年营业收入增长额/上年营业收入总额
B27: 营业利润增长率=本年营业利润增长额/上年营业利润总额
B28: 总资产增长率=本年总资产增长额/年初资产总额
B29: 资本积累率=本年所有者权益增长额/年初所有者权益
B30: 资本保值增值率=扣除客观因素后年末所有者权益额/年初所有者权益
A31: 其他常用财务指标 | B31: 每股净资产=净资产/实收资本（股本） | C31: =资产负债表!H78/资产负债表!H60 -> #DIV/0!
B32: 非上市公司每股收益率=净利润/实收资本（股本） | C32: =利润表!C37/资产负债表!H60 -> #DIV/0!
B33: 上市公司每股收益率=(收盘价-买入价)/买入价
A34: 杜邦财务分析体系（The Du Pont System) | B34: 净资产收益率=销售利润率*总资产周转率*权益乘数 | C34: =C18*C16*C10 -> #DIV/0!
